Workbook

Sheet Executive Summary
A1: KUSHWAHA TENT AJENCY
A2: Executive Business Performance, Sales, & Inventory Overview
A3: Location: Umesh Cinema Road, Hajipur - 844101, Bihar | Phone: 9431658931 | GSTIN: 10AYYPK5118M1Z1 | Period: Feb 2023 – Dec 2025
A5: 1. KEY FINANCIAL PERFORMANCE INDICATORS
A6: Metric Description | B6: Amount / Count | C6: Calculation / Source Sheet | D6: Notes
A7: Total Sales Invoiced | B7: ='Sales Invoices'!E183 -> 15303831 | C7: 'Sales Invoices'!E183 | D7: Total gross sales across 178 tax invoices
A8: Total Upfront Payments on Invoices | B8: ='Sales Invoices'!F183 -> 1025389 | C8: 'Sales Invoices'!F183 | D8: Immediate cash/bank received at time of invoice creation
A9: Total Outstanding on Invoices | B9: ='Sales Invoices'!G183 -> 14278442 | C9: 'Sales Invoices'!G183 | D9: Remaining unpaid balance on sales invoices
A10: Total Payments Received (Receipts) | B10: =SUMIF('Payments & Receipts'!D5:D215,"Payment In (Receipt)",'Payments & Receipts'!F5:F215) -> 9576476 | C10: 'Payments & Receipts' sheet | D10: Collections against past dues across 209 payment entries
A11: Total Outgoing Payments (Disbursements) | B11: =SUMIF('Payments & Receipts'!D5:D215,"Payment Out",'Payments & Receipts'!F5:F215) -> 250000 | C11: 'Payments & Receipts' sheet | D11: Disbursements to suppliers/vendors (Tent studio)
A12: Total Customer Outstanding Ledger Balances | B12: ='Parties Ledger'!H42 -> 4875466 | C12: 'Parties Ledger'!H42 | D12: Cumulative net receivables currently recorded in customer ledger
A13: Total Active Product Catalog SKUs | B13: =COUNTA('Item Master & Stock'!C5:C111) -> 107 | C13: 'Item Master & Stock'!C5:C111 | D13: Total number of unique items and materials in catalog
A14: Total Customers & Business Parties | B14: =COUNTA('Parties Ledger'!B5:B41) -> 37 | C14: 'Parties Ledger'!B5:B41 | D14: Total registered customer, vendor, and expense accounts
A17: 2. TOP 10 CUSTOMERS BY TOTAL SALES REVENUE
A18: Rank | B18: Customer / Party Name | C18: Contact Number | D18: Invoices Count | E18: Total Invoiced (₹) | F18: Current Balance (₹)
A19: 1 | B19: New kushwaha Tent Ajency Mahnar | C19: - | D19: 77 | E19: 8996661.8 | F19: 894263.76
A20: 2 | B20: Maharani electric and tent spare | C20: 80027 21806 | D20: 22 | E20: 2033948.3 | F20: 2033948.3
A21: 3 | B21: Hariyali Machinery and Electric | C21: 82929 25700 | D21: 23 | E21: 1133442.5 | F21: 33984.51
A22: 4 | B22: Pankaj tent house | C22: 8002721806 | D22: 18 | E22: 1092723 | F22: 1034409
A23: 5 | B23: Sohan Dj Sound | C23: 9304740919 | D23: 11 | E23: 543978.94 | F23: 8978.94
A24: 6 | B24: Rajiv tent house | C24: 8709715058 | D24: 2 | E24: 220400 | F24: 136400
A25: 7 | B25: Sonu kumar | C25: 8757293627 | D25: 1 | E25: 123000 | F25: 50000
A26: 8 | B26: J.P.K Enterprise | C26: 9431487455 | D26: 1 | E26: 120055 | F26: 0
A27: 9 | B27: Raja tent house | C27: 7488020540 | D27: 1 | E27: 113490 | F27: 63490
A28: 10 | B28: Abhishek and Arushi Enterprises | C28: 9097537676 | D28: 3 | E28: 101640 | F28: 21000
A30: 3. TOP 10 SELLING PRODUCTS & MATERIALS BY REVENUE
A31: Rank | B31: Item / Material Name | C31: Category | D31: Total Quantity Sold | E31: Unit | F31: Total Sales Revenue (₹)
A32: 1 | B32: clothes | C32: - | D32: 310973.75 | E32: Mtr | F32: 4985616
A33: 2 | B33: Plastic chair | C33: - | D33: 6973 | E33: Pcs | F33: 1756625
A34: 3 | B34: Avdesh clothes | C34: - | D34: 83980.25 | E34: Mtr | F34: 1413668.3
A35: 4 | B35: Print carpet | C35: - | D35: 145 | E35: Pcs | F35: 749650
A36: 5 | B36: Raj cooler 150ltr white copper | C36: - | D36: 20 | E36: Pcs | F36: 477600
A37: 6 | B37: Chadra table | C37: - | D37: 243 | E37: Pcs | F37: 399650
A38: 7 | B38: Bright clothes | C38: - | D38: 14924.25 | E38: F | F38: 317770.25
A39: 8 | B39: V.I.P chair | C39: - | D39: 346 | E39: Pcs | F39: 313940
A40: 9 | B40: Clothes mtr | C40: - | D40: 16591.5 | E40: Mtr | F40: 293020.44
A41: 10 | B41: Dari | C41: - | D41: 1930 | E41: Pcs | F41: 277110

Sheet Sales Invoices
A1: Kushwaha Tent Ajency — Sales Invoices Register
A2: Master register of all sales invoices issued between Feb 2023 and Dec 2025
A4: Sl No | B4: Invoice No | C4: Date | D4: Customer / Party Name | E4: Total Amount (₹) | F4: Paid Amount (₹) | G4: Balance Due (₹) | H4: Payment Status | I4: Payment Mode | J4: Description / Notes
A5: 1 | B5: 1 | C5: 2023-02-11 | D5: Rajiv tent house | E5: =F5+G5 -> 132400 | F5: 30000 | G5: 102400 | H5: =IF(G5<=0,"Paid",IF(F5>0,"Partial","Unpaid")) -> Partial | I5: Cash
A6: 2 | B6: 2 | C6: 2023-02-12 | D6: Raja tent house | E6: =F6+G6 -> 113490 | F6: 50000 | G6: 63490 | H6: =IF(G6<=0,"Paid",IF(F6>0,"Partial","Unpaid")) -> Partial | I6: Cash
A7: 3 | B7: 3 | C7: 2023-02-12 | D7: Pardeep kumar | E7: =F7+G7 -> 15709.5 | F7: 0 | G7: 15709.5 | H7: =IF(G7<=0,"Paid",IF(F7>0,"Partial","Unpaid")) -> Unpaid | I7: Cash
A8: 4 | B8: 4 | C8: 2023-02-12 | D8: R.D.S palace | E8: =F8+G8 -> 50000 | F8: 0 | G8: 50000 | H8: =IF(G8<=0,"Paid",IF(F8>0,"Partial","Unpaid")) -> Unpaid | I8: Cash
A9: 5 | B9: 5 | C9: 2023-02-14 | D9: gulshan tent house | E9: =F9+G9 -> 36000 | F9: 2000 | G9: 34000 | H9: =IF(G9<=0,"Paid",IF(F9>0,"Partial","Unpaid")) -> Partial | I9: Cash
A10: 6 | B10: 7 | C10: 2023-02-21 | D10: Pankaj tent house | E10: =F10+G10 -> 28647.5 | F10: 0 | G10: 28647.5 | H10: =IF(G10<=0,"Paid",IF(F10>0,"Partial","Unpaid")) -> Unpaid | I10: Cash
A11: 7 | B11: 8 | C11: 2023-03-07 | D11: Sonu kumar | E11: =F11+G11 -> 123000 | F11: 73000 | G11: 50000 | H11: =IF(G11<=0,"Paid",IF(F11>0,"Partial","Unpaid")) -> Partial | I11: Cash | J11: 5000- Account deposit 45000- cash
A12: 8 | B12: 9 | C12: 2023-04-05 | D12: Anil tent house | E12: =F12+G12 -> 45600 | F12: 24000 | G12: 21600 | H12: =IF(G12<=0,"Paid",IF(F12>0,"Partial","Unpaid")) -> Partial | I12: Cash
A13: 9 | B13: 10 | C13: 2023-04-09 | D13: shir ram tent house | E13: =F13+G13 -> 65500 | F13: 65500 | G13: 0 | H13: =IF(G13<=0,"Paid",IF(F13>0,"Partial","Unpaid")) -> Paid | I13: Cash
A14: 10 | B14: 11 | C14: 2023-04-11 | D14: Pankaj tent house | E14: =F14+G14 -> 191577.94 | F14: 58314 | G14: 133263.94 | H14: =IF(G14<=0,"Paid",IF(F14>0,"Partial","Unpaid")) -> Partial | I14: Cash
A15: 11 | B15: 12 | C15: 2023-04-14 | D15: Rajiv tent house | E15: =F15+G15 -> 88000 | F15: 34000 | G15: 54000 | H15: =IF(G15<=0,"Paid",IF(F15>0,"Partial","Unpaid")) -> Partial | I15: Cash
A16: 12 | B16: 13 | C16: 2023-04-14 | D16: Birju singh | E16: =F16+G16 -> 100000 | F16: 50000 | G16: 50000 | H16: =IF(G16<=0,"Paid",IF(F16>0,"Partial","Unpaid")) -> Partial | I16: Cash
A17: 13 | B17: 14 | C17: 2023-04-14 | D17: jitendra tent house | E17: =F17+G17 -> 100000 | F17: 90000 | G17: 10000 | H17: =IF(G17<=0,"Paid",IF(F17>0,"Partial","Unpaid")) -> Partial | I17: Cash
A18: 14 | B18: 16 | C18: 2023-04-19 | D18: Cafe D3 | E18: =F18+G18 -> 37000 | F18: 37000 | G18: 0 | H18: =IF(G18<=0,"Paid",IF(F18>0,"Partial","Unpaid")) -> Paid | I18: Cash
A19: 15 | B19: 17 | C19: 2023-04-21 | D19: Chauhan tent house | E19: =F19+G19 -> 84000 | F19: 84000 | G19: 0 | H19: =IF(G19<=0,"Paid",IF(F19>0,"Partial","Unpaid")) -> Paid | I19: Cash
A20: 16 | B20: 18 | C20: 2023-04-24 | D20: Pankaj tent house | E20: =F20+G20 -> 40945.63 | F20: 0 | G20: 40945.63 | H20: =IF(G20<=0,"Paid",IF(F20>0,"Partial","Unpaid")) -> Unpaid | I20: Cash
A21: 17 | B21: 19 | C21: 2023-04-28 | D21: Pankaj tent house | E21: =F21+G21 -> 23790.75 | F21: 0 | G21: 23790.75 | H21: =IF(G21<=0,"Paid",IF(F21>0,"Partial","Unpaid")) -> Unpaid | I21: Cash
A22: 18 | B22: 20 | C22: 2023-05-09 | D22: Pankaj tent house | E22: =F22+G22 -> 104877.5 | F22: 0 | G22: 104877.5 | H22: =IF(G22<=0,"Paid",IF(F22>0,"Partial","Unpaid")) -> Unpaid | I22: Cash
A23: 19 | B23: 21 | C23: 2023-05-12 | D23: Pankaj tent house | E23: =F23+G23 -> 87045 | F23: 0 | G23: 87045 | H23: =IF(G23<=0,"Paid",IF(F23>0,"Partial","Unpaid")) -> Unpaid | I23: Cash
... A83: 79 | B83: 80 | C83: 2024-05-12 | D83: Cafe D3 | E83: =F83+G83 -> 22500 | F83: 0 | G83: 22500 | H83: =IF(G83<=0,"Paid",IF(F83>0,"Partial","Unpaid")) -> Unpaid | I83: Cash
A84: 80 | B84: 81 | C84: 2024-05-12 | D84: New kushwaha Tent Ajency Mahnar | E84: =F84+G84 -> 125406.5 | F84: 33700 | G84: 91706.5 | H84: =IF(G84<=0,"Paid",IF(F84>0,"Partial","Unpaid")) -> Partial | I84: Cash | J84: table square - 10 p aaya hajipur green carpet- 1 p
A85: 81 | B85: 84 | C85: 2024-05-16 | D85: Sohan Dj Sound | E85: =F85+G85 -> 57000 | F85: 0 | G85: 57000 | H85: =IF(G85<=0,"Paid",IF(F85>0,"Partial","Unpaid")) -> Unpaid | I85: Cash
A86: 82 | B86: 101 | C86: 2024-05-22 | D86: Abhishek and Arushi Enterprises | E86: =F86+G86 -> 40320 | F86: 40320 | G86: 0 | H86: =IF(G86<=0,"Paid",IF(F86>0,"Partial","Unpaid")) -> Paid | I86: Kotak Mahindra Bank
A87: 83 | B87: 82 | C87: 2024-05-28 | D87: New kushwaha Tent Ajency Mahnar | E87: =F87+G87 -> 125000 | F87: 0 | G87: 125000 | H87: =IF(G87<=0,"Paid",IF(F87>0,"Partial","Unpaid")) -> Unpaid | I87: Cash
A88: 84 | B88: 83 | C88: 2024-06-05 | D88: Maharani electric and tent spare | E88: =F88+G88 -> 57349 | F88: 0 | G88: 57349 | H88: =IF(G88<=0,"Paid",IF(F88>0,"Partial","Unpaid")) -> Unpaid | I88: Cash
A89: 85 | B89: 85 | C89: 2024-06-05 | D89: Sohan Dj Sound | E89: =F89+G89 -> 29768 | F89: 0 | G89: 29768 | H89: =IF(G89<=0,"Paid",IF(F89>0,"Partial","Unpaid")) -> Unpaid | I89: Cash
A90: 86 | B90: 86 | C90: 2024-06-07 | D90: New kushwaha Tent Ajency Mahnar | E90: =F90+G90 -> 107453 | F90: 0 | G90: 107453 | H90: =IF(G90<=0,"Paid",IF(F90>0,"Partial","Unpaid")) -> Unpaid | I90: Cash
A91: 87 | B91: 100 | C91: 2024-06-18 | D91: Abhishek and Arushi Enterprises | E91: =F91+G91 -> 40320 | F91: 40320 | G91: 0 | H91: =IF(G91<=0,"Paid",IF(F91>0,"Partial","Unpaid")) -> Paid | I91: Kotak Mahindra Bank
A92: 88 | B92: 87 | C92: 2024-06-22 | D92: New kushwaha Tent Ajency Mahnar | E92: =F92+G92 -> 3900 | F92: 0 | G92: 3900 | H92: =IF(G92<=0,"Paid",IF(F92>0,"Partial","Unpaid")) -> Unpaid | I92: Cash
A93: 89 | B93: 88 | C93: 2024-06-23 | D93: Maharani electric and tent spare | E93: =F93+G93 -> 85165.13 | F93: 0 | G93: 85165.13 | H93: =IF(G93<=0,"Paid",IF(F93>0,"Partial","Unpaid")) -> Unpaid | I93: Cash
A94: 90 | B94: 89 | C94: 2024-06-23 | D94: Sohan Dj Sound | E94: =F94+G94 -> 5776 | F94: 0 | G94: 5776 | H94: =IF(G94<=0,"Paid",IF(F94>0,"Partial","Unpaid")) -> Unpaid | I94: Cash
A95: 91 | B95: 90 | C95: 2024-06-24 | D95: New kushwaha Tent Ajency Mahnar | E95: =F95+G95 -> 54551 | F95: 0 | G95: 54551 | H95: =IF(G95<=0,"Paid",IF(F95>0,"Partial","Unpaid")) -> Unpaid | I95: Cash
A96: 92 | B96: 91 | C96: 2024-07-05 | D96: Hariyali Machinery and Electric | E96: =F96+G96 -> 56196 | F96: 30000 | G96: 26196 | H96: =IF(G96<=0,"Paid",IF(F96>0,"Partial","Unpaid")) -> Partial | I96: Kotak Mahindra Bank
... A165: 161 | B165: 163 | C165: 2025-10-04 | D165: New kushwaha Tent Ajency Mahnar | E165: =F165+G165 -> 99088 | F165: 0 | G165: 99088 | H165: =IF(G165<=0,"Paid",IF(F165>0,"Partial","Unpaid")) -> Unpaid | I165: Kotak Mahindra Bank
A166: 162 | B166: 165 | C166: 2025-10-17 | D166: New kushwaha Tent Ajency Mahnar | E166: =F166+G166 -> 25500 | F166: 0 | G166: 25500 | H166: =IF(G166<=0,"Paid",IF(F166>0,"Partial","Unpaid")) -> Unpaid | I166: Kotak Mahindra Bank | J166: lm niwar
A167: 163 | B167: 164 | C167: 2025-10-25 | D167: New kushwaha Tent Ajency Mahnar | E167: =F167+G167 -> 48800 | F167: 0 | G167: 48800 | H167: =IF(G167<=0,"Paid",IF(F167>0,"Partial","Unpaid")) -> Unpaid | I167: Kotak Mahindra Bank
A168: 164 | B168: 166 | C168: 2025-11-01 | D168: New kushwaha Tent Ajency Mahnar | E168: =F168+G168 -> 17158 | F168: 0 | G168: 17158 | H168: =IF(G168<=0,"Paid",IF(F168>0,"Partial","Unpaid")) -> Unpaid | I168: Kotak Mahindra Bank
A169: 165 | B169: 167 | C169: 2025-11-02 | D169: New kushwaha Tent Ajency Mahnar | E169: =F169+G169 -> 99255 | F169: 0 | G169: 99255 | H169: =IF(G169<=0,"Paid",IF(F169>0,"Partial","Unpaid")) -> Unpaid | I169: Kotak Mahindra Bank
A170: 166 | B170: 168 | C170: 2025-11-11 | D170: Hariyali Machinery and Electric | E170: =F170+G170 -> 54830 | F170: 0 | G170: 54830 | H170: =IF(G170<=0,"Paid",IF(F170>0,"Partial","Unpaid")) -> Unpaid | I170: Kotak Mahindra Bank
A171: 167 | B171: 169 | C171: 2025-11-12 | D171: New kushwaha Tent Ajency Mahnar | E171: =F171+G171 -> 114344.38 | F171: 0 | G171: 114344.38 | H171: =IF(G171<=0,"Paid",IF(F171>0,"Partial","Unpaid")) -> Unpaid | I171: Kotak Mahindra Bank
A172: 168 | B172: 170 | C172: 2025-11-18 | D172: New kushwaha Tent Ajency Mahnar | E172: =F172+G172 -> 124616.25 | F172: 0 | G172: 124616.25 | H172: =IF(G172<=0,"Paid",IF(F172>0,"Partial","Unpaid")) -> Unpaid | I172: Kotak Mahindra Bank
A173: 169 | B173: 171 | C173: 2025-11-20 | D173: New kushwaha Tent Ajency Mahnar | E173: =F173+G173 -> 159362.25 | F173: 0 | G173: 159362.25 | H173: =IF(G173<=0,"Paid",IF(F173>0,"Partial","Unpaid")) -> Unpaid | I173: Kotak Mahindra Bank
A174: 170 | B174: 172 | C174: 2025-11-23 | D174: New kushwaha Tent Ajency Mahnar | E174: =F174+G174 -> 84620.25 | F174: 0 | G174: 84620.25 | H174: =IF(G174<=0,"Paid",IF(F174>0,"Partial","Unpaid")) -> Unpaid | I174: Kotak Mahindra Bank
A175: 171 | B175: 173 | C175: 2025-11-26 | D175: Hariyali Machinery and Electric | E175: =F175+G175 -> 65010.5 | F175: 0 | G175: 65010.5 | H175: =IF(G175<=0,"Paid",IF(F175>0,"Partial","Unpaid")) -> Unpaid | I175: Kotak Mahindra Bank
A176: 172 | B176: 174 | C176: 2025-11-27 | D176: New kushwaha Tent Ajency Mahnar | E176: =F176+G176 -> 131562.25 | F176: 0 | G176: 131562.25 | H176: =IF(G176<=0,"Paid",IF(F176>0,"Partial","Unpaid")) -> Unpaid | I176: Kotak Mahindra Bank
A177: 173 | B177: 175 | C177: 2025-11-28 | D177: Hariyali Machinery and Electric | E177: =F177+G177 -> 26900 | F177: 0 | G177: 26900 | H177: =IF(G177<=0,"Paid",IF(F177>0,"Partial","Unpaid")) -> Unpaid | I177: Kotak Mahindra Bank
A178: 174 | B178: 176 | C178: 2025-12-02 | D178: New kushwaha Tent Ajency Mahnar | E178: =F178+G178 -> 20245.88 | F178: 0 | G178: 20245.88 | H178: =IF(G178<=0,"Paid",IF(F178>0,"Partial","Unpaid")) -> Unpaid | I178: Kotak Mahindra Bank
A179: 175 | B179: 177 | C179: 2025-12-04 | D179: New kushwaha Tent Ajency Mahnar | E179: =F179+G179 -> 51452 | F179: 22680 | G179: 28772 | H179: =IF(G179<=0,"Paid",IF(F179>0,"Partial","Unpaid")) -> Partial | I179: Kotak Mahindra Bank | J179: maharaja :-12,500 hitlon aaya :-38:-9880 gadi bhada:-300
A180: 176 | B180: 178 | C180: 2025-12-23 | D180: Hariyali Machinery and Electric | E180: =F180+G180 -> 28800 | F180: 0 | G180: 28800 | H180: =IF(G180<=0,"Paid",IF(F180>0,"Partial","Unpaid")) -> Unpaid | I180: Kotak Mahindra Bank
A181: 177 | B181: 179 | C181: 2025-12-24 | D181: New kushwaha Tent Ajency Mahnar | E181: =F181+G181 -> 186887.5 | F181: 0 | G181: 186887.5 | H181: =IF(G181<=0,"Paid",IF(F181>0,"Partial","Unpaid")) -> Unpaid | I181: Kotak Mahindra Bank
A182: 178 | B182: 180 | C182: 2025-12-27 | D182: New kushwaha Tent Ajency Mahnar | E182: =F182+G182 -> 47000 | F182: 0 | G182: 47000 | H182: =IF(G182<=0,"Paid",IF(F182>0,"Partial","Unpaid")) -> Unpaid | I182: Kotak Mahindra Bank
D183: Total | E183: =SUM(E5:E182) -> 15303831 | F183: =SUM(F5:F182) -> 1025389 | G183: =SUM(G5:G182) -> 14278442

Sheet Invoice Line Items
A1: Kushwaha Tent Ajency — Detailed Invoice Line Items
A2: Itemized breakdown of products and services per sales invoice
A4: Sl No | B4: Invoice No | C4: Date | D4: Customer Name | E4: Item Name | F4: Category | G4: Quantity | H4: Unit | I4: Unit Price (₹) | J4: Discount (₹) | K4: Tax (₹) | L4: Line Total (₹)
A5: 1 | B5: 1 | C5: 2023-02-11 | D5: Rajiv tent house | E5: V.I.P chair | F5: - | G5: 100 | H5: Pcs | I5: 1200 | J5: 0 | K5: 0 | L5: =G5*I5-J5+K5 -> 120000
A6: 2 | B6: 1 | C6: 2023-02-11 | D6: Rajiv tent house | E6: Sundaram carpet | F6: - | G6: 2 | H6: Pcs | I6: 6200 | J6: 0 | K6: 0 | L6: =G6*I6-J6+K6 -> 12400
A7: 3 | B7: 2 | C7: 2023-02-12 | D7: Raja tent house | E7: Plain clothes | F7: - | G7: 1190 | H7: Mtr | I7: 18 | J7: 0 | K7: 0 | L7: =G7*I7-J7+K7 -> 21420
A8: 4 | B8: 2 | C8: 2023-02-12 | D8: Raja tent house | E8: Dari | F8: - | G8: 20 | H8: Pcs | I8: 200 | J8: 0 | K8: 0 | L8: =G8*I8-J8+K8 -> 4000
A9: 5 | B9: 2 | C9: 2023-02-12 | D9: Raja tent house | E9: Net clothes | F9: - | G9: 260 | H9: F | I9: 12 | J9: 0 | K9: 0 | L9: =G9*I9-J9+K9 -> 3120
A10: 6 | B10: 2 | C10: 2023-02-12 | D10: Raja tent house | E10: Raj coller 150ltr CPG | F10: - | G10: 2 | H10: Pcs | I10: 18500 | J10: 0 | K10: 0 | L10: =G10*I10-J10+K10 -> 37000
A11: 7 | B11: 2 | C11: 2023-02-12 | D11: Raja tent house | E11: Plastic chair | F11: - | G11: 150 | H11: Pcs | I11: 295 | J11: 0 | K11: 0 | L11: =G11*I11-J11+K11 -> 44250
A12: 8 | B12: 2 | C12: 2023-02-12 | D12: Raja tent house | E12: Phle ka baki paisa | F12: - | G12: 1 | I12: 3700 | J12: 0 | K12: 0 | L12: =G12*I12-J12+K12 -> 3700
A13: 9 | B13: 3 | C13: 2023-02-12 | D13: Pardeep kumar | E13: Plain clothes | F13: - | G13: 872.75 | H13: Mtr | I13: 18 | J13: 0 | K13: 0 | L13: =G13*I13-J13+K13 -> 15709.5
A14: 10 | B14: 4 | C14: 2023-02-12 | D14: R.D.S palace | E14: Raj cooler 150ltr white copper | F14: - | G14: 2 | H14: Pcs | I14: 25000 | J14: 0 | K14: 0 | L14: =G14*I14-J14+K14 -> 50000
A15: 11 | B15: 5 | C15: 2023-02-14 | D15: gulshan tent house | E15: Raj coller 150ltr CPG | F15: - | G15: 2 | H15: Pcs | I15: 18500 | J15: 1000 | K15: 0 | L15: =G15*I15-J15+K15 -> 36000
A16: 12 | B16: 7 | C16: 2023-02-21 | D16: Pankaj tent house | E16: Avdesh clothes | F16: - | G16: 1197 | H16: Mtr | I16: 17.5 | J16: 0 | K16: 0 | L16: =G16*I16-J16+K16 -> 20947.5
A17: 13 | B17: 7 | C17: 2023-02-21 | D17: Pankaj tent house | E17: Sidhi chota | F17: - | G17: 4 | H17: Pcs | I17: 1125 | J17: 0 | K17: 0 | L17: =G17*I17-J17+K17 -> 4500
A18: 14 | B18: 7 | C18: 2023-02-21 | D18: Pankaj tent house | E18: Sidhi 10ft | F18: - | G18: 2 | I18: 1600 | J18: 0 | K18: 0 | L18: =G18*I18-J18+K18 -> 3200
A19: 15 | B19: 8 | C19: 2023-03-07 | D19: Sonu kumar | E19: Raj cooler 150ltr white copper | F19: - | G19: 4 | H19: Pcs | I19: 24000 | J19: 2000 | K19: 0 | L19: =G19*I19-J19+K19 -> 94000
A20: 16 | B20: 8 | C20: 2023-03-07 | D20: Sonu kumar | E20: Plastic chair | F20: - | G20: 100 | H20: Pcs | I20: 290 | J20: 0 | K20: 0 | L20: =G20*I20-J20+K20 -> 29000
A21: 17 | B21: 9 | C21: 2023-04-05 | D21: Anil tent house | E21: Raj cooler 150ltr white copper | F21: - | G21: 2 | H21: Pcs | I21: 22800 | J21: 0 | K21: 0 | L21: =G21*I21-J21+K21 -> 45600
A22: 18 | B22: 10 | C22: 2023-04-09 | D22: shir ram tent house | E22: Raj coller 150 APG | F22: - | G22: 4 | H22: Pcs | I22: 16400 | J22: 100 | K22: 0 | L22: =G22*I22-J22+K22 -> 65500
A23: 19 | B23: 11 | C23: 2023-04-11 | D23: Pankaj tent house | E23: Avdesh clothes | F23: - | G23: 10708.75 | H23: Mtr | I23: 17.25 | J23: 0 | K23: 0 | L23: =G23*I23-J23+K23 -> 184725.94
A24: 20 | B24: 11 | C24: 2023-04-11 | D24: Pankaj tent house | E24: Bright clothes | F24: - | G24: 285.5 | H24: F | I24: 24 | J24: 0 | K24: 0 | L24: =G24*I24-J24+K24 -> 6852
A25: 21 | B25: 12 | C25: 2023-04-14 | D25: Rajiv tent house | E25: Raj cooler 150ltr white copper | F25: - | G25: 4 | H25: Pcs | I25: 22000 | J25: 0 | K25: 0 | L25: =G25*I25-J25+K25 -> 88000
A26: 22 | B26: 13 | C26: 2023-04-14 | D26: Birju singh | E26: Raj cooler 150ltr white copper | F26: - | G26: 4 | H26: Pcs | I26: 25000 | J26: 0 | K26: 0 | L26: =G26*I26-J26+K26 -> 100000
A27: 23 | B27: 14 | C27: 2023-04-14 | D27: jitendra tent house | E27: Raj cooler 150ltr white copper | F27: - | G27: 4 | H27: Pcs | I27: 25000 | J27: 0 | K27: 0 | L27: =G27*I27-J27+K27 -> 100000
A28: 24 | B28: 16 | C28: 2023-04-19 | D28: Cafe D3 | E28: Raj coller 150ltr CPG | F28: - | G28: 2 | H28: Pcs | I28: 18500 | J28: 0 | K28: 0 | L28: =G28*I28-J28+K28 -> 37000
A29: 25 | B29: 17 | C29: 2023-04-21 | D29: Chauhan tent house | E29: Raj cooler 150ltr white copper 3 blade | F29: - | G29: 4 | H29: Pcs | I29: 21000 | J29: 0 | K29: 0 | L29: =G29*I29-J29+K29 -> 84000
A30: 26 | B30: 18 | C30: 2023-04-24 | D30: Pankaj tent house | E30: Avdesh clothes | F30: - | G30: 2339.75 | H30: Mtr | I30: 17.5 | J30: 0 | K30: 0 | L30: =G30*I30-J30+K30 -> 40945.625
... A47: 43 | B47: 30 | C47: 2023-08-16 | D47: Pankaj tent house | E47: Avdesh clothes | F47: - | G47: 1841 | H47: Mtr | I47: 16.5 | J47: 0 | K47: 0 | L47: =G47*I47-J47+K47 -> 30376.5
A48: 44 | B48: 30 | C48: 2023-08-16 | D48: Pankaj tent house | E48: Phle ka baki paisa | F48: - | G48: 1 | I48: 1000 | J48: 0 | K48: 0 | L48: =G48*I48-J48+K48 -> 1000
A49: 45 | B49: 31 | C49: 2023-10-03 | D49: Maharani electric and tent spare | E49: Avdesh clothes | F49: - | G49: 13374.25 | H49: Mtr | I49: 16 | J49: 0 | K49: 0 | L49: =G49*I49-J49+K49 -> 213988
A50: 46 | B50: 32 | C50: 2023-10-05 | D50: Maharani electric and tent spare | E50: Avdesh clothes | F50: - | G50: 4595.25 | H50: Mtr | I50: 16 | J50: 0 | K50: 0 | L50: =G50*I50-J50+K50 -> 73524
A51: 47 | B51: 33 | C51: 2023-11-24 | D51: Pankaj tent house | E51: clothes | F51: - | G51: 5912 | H51: Mtr | I51: 16.25 | J51: 0 | K51: 0 | L51: =G51*I51-J51+K51 -> 96070
A52: 48 | B52: 33 | C52: 2023-11-24 | D52: Pankaj tent house | E52: Sidhi chota | F52: - | G52: 4 | H52: Pcs | I52: 1125 | J52: 0 | K52: 0 | L52: =G52*I52-J52+K52 -> 4500
A53: 49 | B53: 33 | C53: 2023-11-24 | D53: Pankaj tent house | E53: Sidhi 10ft | F53: - | G53: 1 | I53: 1700 | J53: 0 | K53: 0 | L53: =G53*I53-J53+K53 -> 1700
A54: 50 | B54: 33 | C54: 2023-11-24 | D54: Pankaj tent house | E54: Patiya | F54: - | G54: 499 | H54: Mtr | I54: 12.5 | J54: 0 | K54: 0 | L54: =G54*I54-J54+K54 -> 6237.5
A55: 51 | B55: 34 | C55: 2023-12-05 | D55: Pankaj tent house | E55: Safeda | F55: - | G55: 185.7 | H55: Mtr | I55: 55 | J55: 0 | K55: 0 | L55: =G55*I55-J55+K55 -> 10213.5
A56: 52 | B56: 34 | C56: 2023-12-05 | D56: Pankaj tent house | E56: clothes | F56: - | G56: 4980.75 | H56: Mtr | I56: 16.25 | J56: 0 | K56: 0 | L56: =G56*I56-J56+K56 -> 80937.188
A57: 53 | B57: 36 | C57: 2023-12-12 | D57: Pankaj tent house | E57: clothes | F57: - | G57: 1588.5 | H57: Mtr | I57: 16 | J57: 0 | K57: 0 | L57: =G57*I57-J57+K57 -> 25416
A58: 54 | B58: 36 | C58: 2023-12-12 | D58: Pankaj tent house | E58: Sidhi chota | F58: - | G58: 10 | H58: Pcs | I58: 1150 | J58: 0 | K58: 0 | L58: =G58*I58-J58+K58 -> 11500
A59: 55 | B59: 36 | C59: 2023-12-12 | D59: Pankaj tent house | E59: Sidhi 10ft | F59: - | G59: 5 | I59: 1700 | J59: 0 | K59: 0 | L59: =G59*I59-J59+K59 -> 8500
A60: 56 | B60: 35 | C60: 2023-12-13 | D60: J.P.K Enterprise | E60: Avdesh clothes | F60: - | G60: 600 | H60: Mtr | I60: 17.5 | J60: 0 | K60: 525 | L60: =G60*I60-J60+K60 -> 11025
A61: 57 | B61: 35 | C61: 2023-12-13 | D61: J.P.K Enterprise | E61: Table square | F61: - | G61: 25 | H61: Pcs | I61: 2500 | J61: 0 | K61: 11250 | L61: =G61*I61-J61+K61 -> 73750
A62: 58 | B62: 35 | C62: 2023-12-13 | D62: J.P.K Enterprise | E62: Sundaram carpet | F62: - | G62: 7 | H62: Pcs | I62: 4500 | J62: 0 | K62: 3780 | L62: =G62*I62-J62+K62 -> 35280
A63: 59 | B63: 37 | C63: 2023-12-26 | D63: Maharani electric and tent spare | E63: clothes | F63: - | G63: 5197 | H63: Mtr | I63: 16 | J63: 0 | K63: 0 | L63: =G63*I63-J63+K63 -> 83152
A64: 60 | B64: 38 | C64: 2024-01-19 | D64: Maharani electric and tent spare | E64: clothes | F64: - | G64: 6214.75 | H64: Mtr | I64: 16 | J64: 0 | K64: 0 | L64: =G64*I64-J64+K64 -> 99436
A65: 61 | B65: 39 | C65: 2024-01-24 | D65: Maharani electric and tent spare | E65: clothes | F65: - | G65: 4393 | H65: Mtr | I65: 16 | J65: 0 | K65: 0 | L65: =G65*I65-J65+K65 -> 70288
A66: 62 | B66: 40 | C66: 2024-01-24 | D66: Maharani electric and tent spare | E66: clothes | F66: - | G66: 4277 | H66: Mtr | I66: 16 | J66: 0 | K66: 0 | L66: =G66*I66-J66+K66 -> 68432
A67: 63 | B67: 41 | C67: 2024-01-31 | D67: Maharani electric and tent spare | E67: clothes | F67: - | G67: 5714.25 | H67: Mtr | I67: 16 | J67: 0 | K67: 0 | L67: =G67*I67-J67+K67 -> 91428
A68: 64 | B68: 42 | C68: 2024-02-08 | D68: New kushwaha Tent Ajency Mahnar | E68: clothes | F68: - | G68: 5631.75 | H68: Mtr | I68: 16.5 | J68: 0 | K68: 0 | L68: =G68*I68-J68+K68 -> 92923.875
A69: 65 | B69: 43 | C69: 2024-02-13 | D69: New kushwaha Tent Ajency Mahnar | E69: Net clothes | F69: - | G69: 1489.25 | H69: F | I69: 11 | J69: 0 | K69: 0 | L69: =G69*I69-J69+K69 -> 16381.75
A70: 66 | B70: 43 | C70: 2024-02-13 | D70: New kushwaha Tent Ajency Mahnar | E70: Safeda | F70: - | G70: 126.1 | H70: Mtr | I70: 58 | J70: 0 | K70: 0 | L70: =G70*I70-J70+K70 -> 7313.8
A71: 67 | B71: 43 | C71: 2024-02-13 | D71: New kushwaha Tent Ajency Mahnar | E71: Sidhi chota | F71: - | G71: 5 | H71: Pcs | I71: 1150 | J71: 0 | K71: 0 | L71: =G71*I71-J71+K71 -> 5750
A72: 68 | B72: 43 | C72: 2024-02-13 | D72: New kushwaha Tent Ajency Mahnar | E72: Sidhi 10ft | F72: - | G72: 3 | I72: 1700 | J72: 0 | K72: 0 | L72: =G72*I72-J72+K72 -> 5100
A73: 69 | B73: 43 | C73: 2024-02-13 | D73: New kushwaha Tent Ajency Mahnar | E73: Parda kamdar | F73: - | G73: 20 | H73: Pcs | I73: 850 | J73: 0 | K73: 0 | L73: =G73*I73-J73+K73 -> 17000
A74: 70 | B74: 43 | C74: 2024-02-13 | D74: New kushwaha Tent Ajency Mahnar | E74: Parda karkat | F74: - | G74: 17 | H74: Pcs | I74: 650 | J74: 0 | K74: 0 | L74: =G74*I74-J74+K74 -> 11050
A75: 71 | B75: 43 | C75: 2024-02-13 | D75: New kushwaha Tent Ajency Mahnar | E75: Jhalar | F75: - | G75: 50 | H75: Pcs | I75: 225 | J75: 0 | K75: 0 | L75: =G75*I75-J75+K75 -> 11250
A76: 72 | B76: 43 | C76: 2024-02-13 | D76: New kushwaha Tent Ajency Mahnar | E76: Print carpet | F76: - | G76: 11 | H76: Pcs | I76: 5500 | J76: 0 | K76: 0 | L76: =G76*I76-J76+K76 -> 60500
A77: 73 | B77: 43 | C77: 2024-02-13 | D77: New kushwaha Tent Ajency Mahnar | E77: Sundaram carpet red | F77: - | G77: 2 | I77: 6000 | J77: 0 | K77: 0 | L77: =G77*I77-J77+K77 -> 12000
A78: 74 | B78: 43 | C78: 2024-02-13 | D78: New kushwaha Tent Ajency Mahnar | E78: Sundaram carpet green | F78: - | G78: 2 | I78: 5700 | J78: 0 | K78: 0 | L78: =G78*I78-J78+K78 -> 11400
A79: 75 | B79: 43 | C79: 2024-02-13 | D79: New kushwaha Tent Ajency Mahnar | E79: Chadra table | F79: - | G79: 10 | H79: Pcs | I79: 1700 | J79: 0 | K79: 0 | L79: =G79*I79-J79+K79 -> 17000
A80: 76 | B80: 43 | C80: 2024-02-13 | D80: New kushwaha Tent Ajency Mahnar | E80: Bright clothes | F80: - | G80: 1715 | H80: F | I80: 20 | J80: 0 | K80: 0 | L80: =G80*I80-J80+K80 -> 34300
A81: 77 | B81: 43 | C81: 2024-02-13 | D81: New kushwaha Tent Ajency Mahnar | E81: clothes | F81: - | G81: 5047.5 | H81: Mtr | I81: 16.5 | J81: 0 | K81: 0 | L81: =G81*I81-J81+K81 -> 83283.75
A82: 78 | B82: 43 | C82: 2024-02-13 | D82: New kushwaha Tent Ajency Mahnar | E82: Print cloth | F82: - | G82: 827.25 | H82: Mtr | I82: 25 | J82: 0 | K82: 0 | L82: =G82*I82-J82+K82 -> 20681.25
A83: 79 | B83: 43 | C83: 2024-02-13 | D83: New kushwaha Tent Ajency Mahnar | E83: Patiya | F83: - | G83: 367 | H83: Mtr | I83: 16 | J83: 0 | K83: 0 | L83: =G83*I83-J83+K83 -> 5872
A84: 80 | B84: 43 | C84: 2024-02-13 | D84: New kushwaha Tent Ajency Mahnar | E84: Patiya kapra wala | F84: - | G84: 282 | H84: Pcs | I84: 13 | J84: 0 | K84: 0 | L84: =G84*I84-J84+K84 -> 3666
A85: 81 | B85: 43 | C85: 2024-02-13 | D85: New kushwaha Tent Ajency Mahnar | E85: Tripal 18*24 | F85: - | G85: 3 | H85: Pcs | I85: 1600 | J85: 0 | K85: 0 | L85: =G85*I85-J85+K85 -> 4800
A86: 82 | B86: 43 | C86: 2024-02-13 | D86: New kushwaha Tent Ajency Mahnar | E86: Tripal 21*30 | F86: - | G86: 2 | I86: 2100 | J86: 0 | K86: 0 | L86: =G86*I86-J86+K86 -> 4200
A87: 83 | B87: 43 | C87: 2024-02-13 | D87: New kushwaha Tent Ajency Mahnar | E87: Dari | F87: - | G87: 120 | H87: Pcs | I87: 200 | J87: 0 | K87: 0 | L87: =G87*I87-J87+K87 -> 24000
A88: 84 | B88: 43 | C88: 2024-02-13 | D88: New kushwaha Tent Ajency Mahnar | E88: Flode clothes | F88: - | G88: 5566.5 | H88: F | I88: 10.5 | J88: 0 | K88: 0 | L88: =G88*I88-J88+K88 -> 58448.25
A89: 85 | B89: 43 | C89: 2024-02-13 | D89: New kushwaha Tent Ajency Mahnar | E89: Plastic chair | F89: - | G89: 300 | H89: Pcs | I89: 255 | J89: 0 | K89: 0 | L89: =G89*I89-J89+K89 -> 76500
A90: 86 | B90: 44 | C90: 2024-02-16 | D90: New kushwaha Tent Ajency Mahnar | E90: Safeda | F90: - | G90: 60.7 | H90: Mtr | I90: 58 | J90: 0 | K90: 0 | L90: =G90*I90-J90+K90 -> 3520.6
A91: 87 | B91: 44 | C91: 2024-02-16 | D91: New kushwaha Tent Ajency Mahnar | E91: V.I.P chair | F91: - | G91: 50 | H91: Pcs | I91: 790 | J91: 0 | K91: 0 | L91: =G91*I91-J91+K91 -> 39500
A92: 88 | B92: 44 | C92: 2024-02-16 | D92: New kushwaha Tent Ajency Mahnar | E92: Plastic chair | F92: - | G92: 50 | H92: Pcs | I92: 255 | J92: 0 | K92: 0 | L92: =G92*I92-J92+K92 -> 12750
A93: 89 | B93: 44 | C93: 2024-02-16 | D93: New kushwaha Tent Ajency Mahnar | E93: clothes | F93: - | G93: 633 | H93: Mtr | I93: 16.5 | J93: 0 | K93: 0 | L93: =G93*I93-J93+K93 -> 10444.5
A94: 90 | B94: 45 | C94: 2024-02-20 | D94: New kushwaha Tent Ajency Mahnar | E94: Maharaja | F94: - | G94: 5 | H94: Pcs | I94: 8500 | J94: 0 | K94: 0 | L94: =G94*I94-J94+K94 -> 42500
A95: 91 | B95: 45 | C95: 2024-02-20 | D95: New kushwaha Tent Ajency Mahnar | E95: Maharaja | F95: - | G95: 1 | H95: Pcs | I95: 6300 | J95: 0 | K95: 0 | L95: =G95*I95-J95+K95 -> 6300
A96: 92 | B96: 45 | C96: 2024-02-20 | D96: New kushwaha Tent Ajency Mahnar | E96: Parda karkat | F96: - | G96: 650 | H96: Pcs | I96: 10 | J96: 0 | K96: 0 | L96: =G96*I96-J96+K96 -> 6500
A97: 93 | B97: 45 | C97: 2024-02-20 | D97: New kushwaha Tent Ajency Mahnar | E97: Safeda | F97: - | G97: 133.3 | H97: Mtr | I97: 58 | J97: 0 | K97: 0 | L97: =G97*I97-J97+K97 -> 7731.4
A98: 94 | B98: 45 | C98: 2024-02-20 | D98: New kushwaha Tent Ajency Mahnar | E98: clothes | F98: - | G98: 671.75 | H98: Mtr | I98: 16.5 | J98: 0 | K98: 0 | L98: =G98*I98-J98+K98 -> 11083.875
... A112: 108 | B112: 47 | C112: 2024-02-25 | D112: New kushwaha Tent Ajency Mahnar | E112: Round jhumar | F112: - | G112: 10 | H112: Pcs | I112: 325 | J112: 0 | K112: 0 | L112: =G112*I112-J112+K112 -> 3250
A113: 109 | B113: 47 | C113: 2024-02-25 | D113: New kushwaha Tent Ajency Mahnar | E113: Nagin jhumar | F113: - | G113: 10 | I113: 275 | J113: 0 | K113: 0 | L113: =G113*I113-J113+K113 -> 2750
A114: 110 | B114: 47 | C114: 2024-02-25 | D114: New kushwaha Tent Ajency Mahnar | E114: 3 tala jhumar | F114: - | G114: 10 | H114: Pcs | I114: 300 | J114: 0 | K114: 0 | L114: =G114*I114-J114+K114 -> 3000
A115: 111 | B115: 47 | C115: 2024-02-25 | D115: New kushwaha Tent Ajency Mahnar | E115: Print cloth | F115: - | G115: 838.5 | H115: Mtr | I115: 25 | J115: 0 | K115: 0 | L115: =G115*I115-J115+K115 -> 20962.5
A116: 112 | B116: 47 | C116: 2024-02-25 | D116: New kushwaha Tent Ajency Mahnar | E116: Safeda | F116: - | G116: 72.8 | H116: Mtr | I116: 58 | J116: 0 | K116: 0 | L116: =G116*I116-J116+K116 -> 4222.4
A117: 113 | B117: 47 | C117: 2024-02-25 | D117: New kushwaha Tent Ajency Mahnar | E117: clothes | F117: - | G117: 661 | H117: Mtr | I117: 16.5 | J117: 0 | K117: 0 | L117: =G117*I117-J117+K117 -> 10906.5
A118: 114 | B118: 47 | C118: 2024-02-25 | D118: New kushwaha Tent Ajency Mahnar | E118: Flode clothes | F118: - | G118: 6892 | H118: F | I118: 10.5 | J118: 0 | K118: 0 | L118: =G118*I118-J118+K118 -> 72366
A119: 115 | B119: 47 | C119: 2024-02-25 | D119: New kushwaha Tent Ajency Mahnar | E119: Niwar | F119: - | G119: 5 | H119: Pcs | I119: 200 | J119: 0 | K119: 0 | L119: =G119*I119-J119+K119 -> 1000
A120: 116 | B120: 48 | C120: 2024-02-26 | D120: Maharani electric and tent spare | E120: clothes | F120: - | G120: 3160.75 | H120: Mtr | I120: 16 | J120: 0 | K120: 0 | L120: =G120*I120-J120+K120 -> 50572
A121: 117 | B121: 48 | C121: 2024-02-26 | D121: Maharani electric and tent spare | E121: Patiya | F121: - | G121: 553 | H121: Mtr | I121: 16 | J121: 0 | K121: 0 | L121: =G121*I121-J121+K121 -> 8848
A122: 118 | B122: 48 | C122: 2024-02-26 | D122: Maharani electric and tent spare | E122: Bright clothes | F122: - | G122: 707 | H122: F | I122: 19.5 | J122: 0 | K122: 0 | L122: =G122*I122-J122+K122 -> 13786.5
A123: 119 | B123: 49 | C123: 2024-02-28 | D123: New kushwaha Tent Ajency Mahnar | E123: On selling 10*15 | F123: - | G123: 4 | I123: 850 | J123: 0 | K123: 0 | L123: =G123*I123-J123+K123 -> 3400
A124: 120 | B124: 49 | C124: 2024-02-28 | D124: New kushwaha Tent Ajency Mahnar | E124: On selling 15*15 | F124: - | G124: 3 | H124: Pcs | I124: 1250 | J124: 0 | K124: 0 | L124: =G124*I124-J124+K124 -> 3750
A125: 121 | B125: 50 | C125: 2024-03-02 | D125: New kushwaha Tent Ajency Mahnar | E125: Flower | F125: - | G125: 4.15 | H125: Kg | I125: 600 | J125: 0 | K125: 0 | L125: =G125*I125-J125+K125 -> 2490
A126: 122 | B126: 50 | C126: 2024-03-02 | D126: New kushwaha Tent Ajency Mahnar | E126: Jhalar | F126: - | G126: 5 | H126: Pcs | I126: 400 | J126: 0 | K126: 0 | L126: =G126*I126-J126+K126 -> 2000
A127: 123 | B127: 50 | C127: 2024-03-02 | D127: New kushwaha Tent Ajency Mahnar | E127: Chadra table | F127: - | G127: 60 | H127: Pcs | I127: 1700 | J127: 0 | K127: 0 | L127: =G127*I127-J127+K127 -> 102000
A128: 124 | B128: 51 | C128: 2024-03-05 | D128: New kushwaha Tent Ajency Mahnar | E128: Patiya | F128: - | G128: 563 | H128: Mtr | I128: 16 | J128: 0 | K128: 0 | L128: =G128*I128-J128+K128 -> 9008
A129: 125 | B129: 51 | C129: 2024-03-05 | D129: New kushwaha Tent Ajency Mahnar | E129: Plastic chair | F129: - | G129: 500 | H129: Pcs | I129: 255 | J129: 0 | K129: 0 | L129: =G129*I129-J129+K129 -> 127500
A130: 126 | B130: 51 | C130: 2024-03-05 | D130: New kushwaha Tent Ajency Mahnar | E130: Samyana | F130: - | G130: 1 | H130: Pcs | I130: 4000 | J130: 0 | K130: 0 | L130: =G130*I130-J130+K130 -> 4000
...

Sheet Payments & Receipts
A1: Kushwaha Tent Ajency — Payments & Receipts Register
A2: Money receipts from customers (Payment-In) and vendor/expense disbursements (Payment-Out)
A4: Sl No | B4: Receipt / Ref No | C4: Date | D4: Voucher Type | E4: Party Name | F4: Amount (₹) | G4: Payment Mode | H4: Notes / Reference
A5: 1 | B5: 1 | C5: 2023-02-11 | D5: Payment In (Receipt) | E5: Rajiv tent house | F5: 20000 | G5: Cash
A6: 2 | B6: 2 | C6: 2023-04-16 | D6: Payment In (Receipt) | E6: Guddu shaa | F6: 25000 | G6: Cash
A7: 3 | B7: REC-37 | C7: 2023-10-28 | D7: Payment Out | E7: Tent studio | F7: 100000 | G7: Cash
A8: 4 | B8: REC-36 | C8: 2023-11-10 | D8: Payment Out | E8: Tent studio | F8: 150000 | G8: Cash
A9: 5 | B9: 3 | C9: 2024-02-12 | D9: Payment In (Receipt) | E9: New kushwaha Tent Ajency Mahnar | F9: 45000 | G9: Cash
A10: 6 | B10: 4 | C10: 2024-02-17 | D10: Payment In (Receipt) | E10: New kushwaha Tent Ajency Mahnar | F10: 40000 | G10: Cash
A11: 7 | B11: 5 | C11: 2024-02-17 | D11: Payment In (Receipt) | E11: New kushwaha Tent Ajency Mahnar | F11: 31000 | G11: Cheque
A12: 8 | B12: 6 | C12: 2024-02-20 | D12: Payment In (Receipt) | E12: New kushwaha Tent Ajency Mahnar | F12: 26000 | G12: Cash | H12: 600 rajkumar thela 400 thela cash -25000 received hua
A13: 9 | B13: 7 | C13: 2024-02-22 | D13: Payment In (Receipt) | E13: New kushwaha Tent Ajency Mahnar | F13: 80000 | G13: Cash
A14: 10 | B14: 8 | C14: 2024-02-23 | D14: Payment In (Receipt) | E14: New kushwaha Tent Ajency Mahnar | F14: 10000 | G14: Cheque
A15: 11 | B15: 9 | C15: 2024-02-28 | D15: Payment In (Receipt) | E15: New kushwaha Tent Ajency Mahnar | F15: 65000 | G15: Cash
A16: 12 | B16: 18 | C16: 2024-02-28 | D16: Payment In (Receipt) | E16: D green | F16: 25000 | G16: Kotak Mahindra Bank
A17: 13 | B17: 10 | C17: 2024-03-01 | D17: Payment In (Receipt) | E17: New kushwaha Tent Ajency Mahnar | F17: 15500 | G17: Cash
A18: 14 | B18: 11 | C18: 2024-03-04 | D18: Payment In (Receipt) | E18: New kushwaha Tent Ajency Mahnar | F18: 40000 | G18: Cash
A19: 15 | B19: 13 | C19: 2024-03-05 | D19: Payment In (Receipt) | E19: New kushwaha Tent Ajency Mahnar | F19: 17000 | G19: Cash
A20: 16 | B20: 12 | C20: 2024-03-06 | D20: Payment In (Receipt) | E20: New kushwaha Tent Ajency Mahnar | F20: 45000 | G20: Cash
A21: 17 | B21: 14 | C21: 2024-03-14 | D21: Payment In (Receipt) | E21: New kushwaha Tent Ajency Mahnar | F21: 245000 | G21: Cash
A22: 18 | B22: 15 | C22: 2024-03-15 | D22: Payment In (Receipt) | E22: New kushwaha Tent Ajency Mahnar | F22: 14000 | G22: Cash
A23: 19 | B23: 16 | C23: 2024-03-16 | D23: Payment In (Receipt) | E23: New kushwaha Tent Ajency Mahnar | F23: 30000 | G23: Kotak Mahindra Bank
A24: 20 | B24: 17 | C24: 2024-03-18 | D24: Payment In (Receipt) | E24: New kushwaha Tent Ajency Mahnar | F24: 70000 | G24: Cash
... A28: 24 | B28: 22 | C28: 2024-04-05 | D28: Payment In (Receipt) | E28: New kushwaha Tent Ajency Mahnar | F28: 50000 | G28: Kotak Mahindra Bank
A29: 25 | B29: 23 | C29: 2024-04-06 | D29: Payment In (Receipt) | E29: New kushwaha Tent Ajency Mahnar | F29: 86000 | G29: Cash | H29: chair 100p
A30: 26 | B30: 24 | C30: 2024-04-07 | D30: Payment In (Receipt) | E30: New kushwaha Tent Ajency Mahnar | F30: 62000 | G30: Cash
A31: 27 | B31: 25 | C31: 2024-04-07 | D31: Payment In (Receipt) | E31: New kushwaha Tent Ajency Mahnar | F31: 57000 | G31: Cash
A32: 28 | B32: 26 | C32: 2024-04-11 | D32: Payment In (Receipt) | E32: Sohan Dj Sound | F32: 10000 | G32: Cash
A33: 29 | B33: 27 | C33: 2024-04-12 | D33: Payment In (Receipt) | E33: New kushwaha Tent Ajency Mahnar | F33: 50000 | G33: Kotak Mahindra Bank
A34: 30 | B34: 28 | C34: 2024-04-12 | D34: Payment In (Receipt) | E34: New kushwaha Tent Ajency Mahnar | F34: 135000 | G34: Cash
A35: 31 | B35: 29 | C35: 2024-04-15 | D35: Payment In (Receipt) | E35: Sohan Dj Sound | F35: 20000 | G35: Cash
A36: 32 | B36: 30 | C36: 2024-04-17 | D36: Payment In (Receipt) | E36: New kushwaha Tent Ajency Mahnar | F36: 150000 | G36: Cash
A37: 33 | B37: 31 | C37: 2024-04-18 | D37: Payment In (Receipt) | E37: New kushwaha Tent Ajency Mahnar | F37: 20000 | G37: Kotak Mahindra Bank
A38: 34 | B38: 32 | C38: 2024-04-18 | D38: Payment In (Receipt) | E38: New kushwaha Tent Ajency Mahnar | F38: 3000 | G38: Cash
A39: 35 | B39: 33 | C39: 2024-04-20 | D39: Payment In (Receipt) | E39: Sohan Dj Sound | F39: 30000 | G39: Cash
A40: 36 | B40: 34 | C40: 2024-04-20 | D40: Payment In (Receipt) | E40: New shrivastav Tent Ajency | F40: 5000 | G40: Cash
A41: 37 | B41: 35 | C41: 2024-04-21 | D41: Payment In (Receipt) | E41: New kushwaha Tent Ajency Mahnar | F41: 80000 | G41: Kotak Mahindra Bank
... A53: 49 | B53: 47 | C53: 2024-05-02 | D53: Payment In (Receipt) | E53: New kushwaha Tent Ajency Mahnar | F53: 40000 | G53: Kotak Mahindra Bank
A54: 50 | B54: 48 | C54: 2024-05-02 | D54: Payment In (Receipt) | E54: New kushwaha Tent Ajency Mahnar | F54: 10000 | G54: Cash | H54: gadi bhada or tampu bada or parda solve total bada
A55: 51 | B55: 49 | C55: 2024-05-03 | D55: Payment In (Receipt) | E55: Sohan Dj Sound | F55: 20000 | G55: Cash
A56: 52 | B56: 51 | C56: 2024-05-07 | D56: Payment In (Receipt) | E56: New kushwaha Tent Ajency Mahnar | F56: 35000 | G56: Cash
A57: 53 | B57: 50 | C57: 2024-05-09 | D57: Payment In (Receipt) | E57: Sohan Dj Sound | F57: 10000 | G57: Cash
A58: 54 | B58: 52 | C58: 2024-05-13 | D58: Payment In (Receipt) | E58: New kushwaha Tent Ajency Mahnar | F58: 26000 | G58: Cash | H58: Add Mahnar se hajipur tampu bhada -500
A59: 55 | B59: 53 | C59: 2024-05-13 | D59: Payment In (Receipt) | E59: Sohan Dj Sound | F59: 10000 | G59: Cash
A60: 56 | B60: 55 | C60: 2024-05-13 | D60: Payment In (Receipt) | E60: New kushwaha Tent Ajency Mahnar | F60: 111300 | G60: Cash
A61: 57 | B61: 54 | C61: 2024-05-21 | D61: Payment In (Receipt) | E61: New kushwaha Tent Ajency Mahnar | F61: 20000 | G61: Cash
A62: 58 | B62: 56 | C62: 2024-05-28 | D62: Payment In (Receipt) | E62: New kushwaha Tent Ajency Mahnar | F62: 10000 | G62: Kotak Mahindra Bank
A63: 59 | B63: 57 | C63: 2024-05-28 | D63: Payment In (Receipt) | E63: New kushwaha Tent Ajency Mahnar | F63: 20000 | G63: Cash
A64: 60 | B64: 59 | C64: 2024-06-05 | D64: Payment In (Receipt) | E64: Sohan Dj Sound | F64: 10000 | G64: Kotak Mahindra Bank
A65: 61 | B65: 58 | C65: 2024-06-06 | D65: Payment In (Receipt) | E65: New kushwaha Tent Ajency Mahnar | F65: 20000 | G65: Cash | H65: cash+A/c
A66: 62 | B66: 60 | C66: 2024-06-07 | D66: Payment In (Receipt) | E66: Sohan Dj Sound | F66: 5000 | G66: Cash
A67: 63 | B67: 61 | C67: 2024-06-19 | D67: Payment In (Receipt) | E67: New kushwaha Tent Ajency Mahnar | F67: 49000 | G67: Cash
A68: 64 | B68: 62 | C68: 2024-06-21 | D68: Payment In (Receipt) | E68: Sohan Dj Sound | F68: 8000 | G68: Cash
A69: 65 | B69: 63 | C69: 2024-06-22 | D69: Payment In (Receipt) | E69: New kushwaha Tent Ajency Mahnar | F69: 2000 | G69: Cash | H69: auto+ gadi bhada chair ka
A70: 66 | B70: 64 | C70: 2024-07-02 | D70: Payment In (Receipt) | E70: New kushwaha Tent Ajency Mahnar | F70: 44000 | G70: Cash
A71: 67 | B71: 65 | C71: 2024-07-03 | D71: Payment In (Receipt) | E71: Sohan Dj Sound | F71: 10000 | G71: Cash
A72: 68 | B72: 66 | C72: 2024-07-05 | D72: Payment In (Receipt) | E72: New kushwaha Tent Ajency Mahnar | F72: 38000 | G72: Cash
A73: 69 | B73: 67 | C73: 2024-07-06 | D73: Payment In (Receipt) | E73: New kushwaha Tent Ajency Mahnar | F73: 40000 | G73: Cash | H73: payment chair wala
A74: 70 | B74: 68 | C74: 2024-07-06 | D74: Payment In (Receipt) | E74: Hariyali Machinery and Electric | F74: 30000 | G74: Kotak Mahindra Bank
A75: 71 | B75: 69 | C75: 2024-07-07 | D75: Payment In (Receipt) | E75: New kushwaha Tent Ajency Mahnar | F75: 40000 | G75: Kotak Mahindra Bank
A76: 72 | B76: 70 | C76: 2024-07-07 | D76: Payment In (Receipt) | E76: New kushwaha Tent Ajency Mahnar | F76: 35000 | G76: Kotak Mahindra Bank | H76: char wala ko bheja gya
A77: 73 | B77: 71 | C77: 2024-07-08 | D77: Payment In (Receipt) | E77: New kushwaha Tent Ajency Mahnar | F77: 9760 | G77: Kotak Mahindra Bank | H77: chair ka paisa
A78: 74 | B78: 72 | C78: 2024-07-10 | D78: Payment In (Receipt) | E78: New kushwaha Tent Ajency Mahnar | F78: 130000 | G78: Kotak Mahindra Bank
A79: 75 | B79: 73 | C79: 2024-07-10 | D79: Payment In (Receipt) | E79: Sohan Dj Sound | F79: 20000 | G79: Cash
A80: 76 | B80: 74 | C80: 2024-07-14 | D80: Payment In (Receipt) | E80: New kushwaha Tent Ajency Mahnar | F80: 65000 | G80: Kotak Mahindra Bank
A81: 77 | B81: 75 | C81: 2024-07-16 | D81: Payment In (Receipt) | E81: Sohan Dj Sound | F81: 10000 | G81: Kotak Mahindra Bank
A82: 78 | B82: 76 | C82: 2024-07-18 | D82: Payment In (Receipt) | E82: Hariyali Machinery and Electric | F82: 14500 | G82: Kotak Mahindra Bank
A83: 79 | B83: 77 | C83: 2024-07-21 | D83: Payment In (Receipt) | E83: New kushwaha Tent Ajency Mahnar | F83: 45000 | G83: Kotak Mahindra Bank | H83: online+ Cash
A84: 80 | B84: 78 | C84: 2024-07-26 | D84: Payment In (Receipt) | E84: Sohan Dj Sound | F84: 10000 | G84: Kotak Mahindra Bank
A85: 81 | B85: 79 | C85: 2024-07-29 | D85: Payment In (Receipt) | E85: Sohan Dj Sound | F85: 5000 | G85: Kotak Mahindra Bank
A86: 82 | B86: 80 | C86: 2024-08-10 | D86: Payment In (Receipt) | E86: Sohan Dj Sound | F86: 10000 | G86: Kotak Mahindra Bank
A87: 83 | B87: 82 | C87: 2024-09-01 | D87: Payment In (Receipt) | E87: New kushwaha Tent Ajency Mahnar | F87: 5000 | G87: Kotak Mahindra Bank
A88: 84 | B88: 83 | C88: 2024-09-04 | D88: Payment In (Receipt) | E88: New kushwaha Tent Ajency Mahnar | F88: 10000 | G88: Kotak Mahindra Bank
A89: 85 | B89: 84 | C89: 2024-09-11 | D89: Payment In (Receipt) | E89: New kushwaha Tent Ajency Mahnar | F89: 13000 | G89: Cash
A90: 86 | B90: 85 | C90: 2024-09-22 | D90: Payment In (Receipt) | E90: New kushwaha Tent Ajency Mahnar | F90: 12000 | G90: Cash
A91: 87 | B91: 86 | C91: 2024-09-24 | D91: Payment In (Receipt) | E91: Sohan Dj Sound | F91: 10000 | G91: Cash
A92: 88 | B92: 87 | C92: 2024-10-01 | D92: Payment In (Receipt) | E92: Hariyali Machinery and Electric | F92: 25000 | G92: Kotak Mahindra Bank
A93: 89 | B93: 88 | C93: 2024-10-04 | D93: Payment In (Receipt) | E93: New kushwaha Tent Ajency Mahnar | F93: 36000 | G93: Kotak Mahindra Bank
A94: 90 | B94: 89 | C94: 2024-10-07 | D94: Payment In (Receipt) | E94: Hariyali Machinery and Electric | F94: 32000 | G94: Kotak Mahindra Bank
A95: 91 | B95: 90 | C95: 2024-10-09 | D95: Payment In (Receipt) | E95: New kushwaha Tent Ajency Mahnar | F95: 43000 | G95: Cash
A96: 92 | B96: 91 | C96: 2024-10-09 | D96: Payment In (Receipt) | E96: Sohan Dj Sound | F96: 10000 | G96: Kotak Mahindra Bank
A97: 93 | B97: 92 | C97: 2024-10-20 | D97: Payment In (Receipt) | E97: New kushwaha Tent Ajency Mahnar | F97: 70000 | G97: Kotak Mahindra Bank | H97: chair ka payment
A98: 94 | B98: 93 | C98: 2024-10-21 | D98: Payment In (Receipt) | E98: New kushwaha Tent Ajency Mahnar | F98: 70000 | G98: Cash
A99: 95 | B99: 94 | C99: 2024-10-27 | D99: Payment In (Receipt) | E99: New kushwaha Tent Ajency Mahnar | F99: 35000 | G99: Cash | H99: A/c kisi or ke bheje name :- Amaan malik
A100: 96 | B100: 95 | C100: 2024-11-02 | D100: Payment In (Receipt) | E100: Hariyali Machinery and Electric | F100: 30000 | G100: Kotak Mahindra Bank
A101: 97 | B101: 96 | C101: 2024-11-02 | D101: Payment In (Receipt) | E101: Sohan Dj Sound | F101: 10000 | G101: Cash
A102: 98 | B102: 97 | C102: 2024-11-02 | D102: Payment In (Receipt) | E102: New kushwaha Tent Ajency Mahnar | F102: 25000 | G102: Kotak Mahindra Bank | H102: aman malik
A103: 99 | B103: 98 | C103: 2024-11-04 | D103: Payment In (Receipt) | E103: New kushwaha Tent Ajency Mahnar | F103: 10000 | G103: Kotak Mahindra Bank | H103: harsh kumar
A104: 100 | B104: 99 | C104: 2024-11-08 | D104: Payment In (Receipt) | E104: New kushwaha Tent Ajency Mahnar | F104: 27000 | G104: Cash | H104: mosa
A105: 101 | B105: 100 | C105: 2024-11-09 | D105: Payment In (Receipt) | E105: New kushwaha Tent Ajency Mahnar | F105: 40000 | G105: Cash
A106: 102 | B106: 101 | C106: 2024-11-15 | D106: Payment In (Receipt) | E106: Sohan Dj Sound | F106: 20000 | G106: Cash
A107: 103 | B107: 102 | C107: 2024-11-15 | D107: Payment In (Receipt) | E107: Hariyali Machinery and Electric | F107: 52000 | G107: Kotak Mahindra Bank
A108: 104 | B108: 103 | C108: 2024-11-16 | D108: Payment In (Receipt) | E108: New kushwaha Tent Ajency Mahnar | F108: 120000 | G108: Kotak Mahindra Bank | H108: chair booking
A109: 105 | B109: 104 | C109: 2024-11-17 | D109: Payment In (Receipt) | E109: New kushwaha Tent Ajency Mahnar | F109: 105000 | G109: Kotak Mahindra Bank
A110: 106 | B110: 105 | C110: 2024-11-18 | D110: Payment In (Receipt) | E110: Hariyali Machinery and Electric | F110: 61000 | G110: Kotak Mahindra Bank
A111: 107 | B111: 106 | C111: 2024-11-21 | D111: Payment In (Receipt) | E111: New kushwaha Tent Ajency Mahnar | F111: 15000 | G111: Kotak Mahindra Bank
A112: 108 | B112: 107 | C112: 2024-11-22 | D112: Payment In (Receipt) | E112: New kushwaha Tent Ajency Mahnar | F112: 116000 | G112: Cash
A113: 109 | B113: 108 | C113: 2024-11-25 | D113: Payment In (Receipt) | E113: New kushwaha Tent Ajency Mahnar | F113: 112000 | G113: Cash
A114: 110 | B114: 109 | C114: 2024-11-25 | D114: Payment In (Receipt) | E114: Hariyali Machinery and Electric | F114: 26600 | G114: Cash
A115: 111 | B115: 110 | C115: 2024-11-26 | D115: Payment In (Receipt) | E115: Sohan Dj Sound | F115: 10000 | G115: Kotak Mahindra Bank
...

Sheet Parties Ledger
A1: Kushwaha Tent Ajency — Parties & Customer Accounts
A2: Customer, supplier, and expense account balances, contact details, and transaction history
A4: Sl No | B4: Party Name | C4: Party Type | D4: Phone Number | E4: Address / City | F4: State | G4: GSTIN | H4: Current Balance (₹) | I4: Invoices Count | J4: Total Invoiced (₹)
A5: 1 | B5: New kushwaha Tent Ajency Mahnar | C5: Customer | D5: - | E5: - | F5: Bihar | G5: - | H5: 894263.76 | I5: 77 | J5: 8996661.8
A6: 2 | B6: Maharani electric and tent spare | C6: Customer | D6: 80027 21806 | E6: BHAGWANPUR N/A WARD NO-13 Bhagwanpur | F6: Bihar | G6: 10BSJPK0507N1ZY | H6: 2033948.3 | I6: 22 | J6: 2033948.3
A7: 3 | B7: Hariyali Machinery and Electric | C7: Customer | D7: 82929 25700 | E7: - | F7: Bihar | G7: - | H7: 33984.51 | I7: 23 | J7: 1133442.5
A8: 4 | B8: Pankaj tent house | C8: Customer | D8: 8002721806 | E8: - | F8: Bihar | G8: - | H8: 1034409 | I8: 18 | J8: 1092723
A9: 5 | B9: Sohan Dj Sound | C9: Customer | D9: 9304740919 | E9: - | F9: Bihar | G9: - | H9: 8978.94 | I9: 11 | J9: 543978.94
A10: 6 | B10: Rajiv tent house | C10: Customer | D10: 8709715058 | E10: - | F10: Bihar | G10: - | H10: 136400 | I10: 2 | J10: 220400
A11: 7 | B11: Sonu kumar | C11: Customer | D11: 8757293627 | E11: - | F11: Bihar | G11: - | H11: 50000 | I11: 1 | J11: 123000
A12: 8 | B12: J.P.K Enterprise | C12: Customer | D12: 9431487455 | E12: JPK ENTERPRISES 01 Rasulpur fatah, Mahua Rasulpur Fateh | F12: Bihar | G12: 10ARYPK2680H1ZL | H12: 0 | I12: 1 | J12: 120055
A13: 9 | B13: Raja tent house | C13: Customer | D13: 7488020540 | E13: - | F13: Bihar | G13: - | H13: 63490 | I13: 1 | J13: 113490
A14: 10 | B14: Abhishek and Arushi Enterprises | C14: Customer | D14: 9097537676 | E14: GROUND NAWADA KALA WARD NO 45 NAWADA KALA WARD NO 45 NAWADA KALA WARD NO 45 Hajipur | F14: Bihar | G14: 10GDUPK8458K1ZT | H14: 21000 | I14: 3 | J14: 101640
A15: 11 | B15: Birju singh | C15: Customer | D15: 9798456561 | E15: - | F15: Bihar | G15: - | H15: 50000 | I15: 1 | J15: 100000
A16: 12 | B16: jitendra tent house | C16: Customer | D16: 9507894145 | E16: - | F16: Bihar | G16: - | H16: 10000 | I16: 1 | J16: 100000
... A41: 37 | B41: Guddu shaa | C41: Customer | D41: 9931083840 | E41: - | F41: Bihar | G41: - | H41: -25000 | I41: 0 | J41: 0
G42: Total | H42: =SUM(H5:H41) -> 4875466 | I42: =SUM(I5:I41) -> 178 | J42: =SUM(J5:J41) -> 15303831

Sheet Item Master & Stock
A1: Kushwaha Tent Ajency — Product Catalog & Stock Inventory
A2: Inventory of tent materials, cloth, chairs, electricals, coolers, and spare parts
A4: Sl No | B4: Item Code | C4: Item Name | D4: Category | E4: Unit | F4: Sale Price (₹) | G4: Purchase Price (₹) | H4: Stock Quantity | I4: Stock Value (₹) | J4: Status
A5: 1 | B5: ITM-048 | C5: 3 tala jhumar | D5: - | E5: Pcs | F5: 300 | G5: 0 | H5: -10 | I5: 0 | J5: Active
A6: 2 | B6: ITM-044 | C6: 5fit red and yellow cloth | D6: - | E6: Mtr | F6: 45 | G6: 0 | H6: -148 | I6: 0 | J6: Active
A7: 3 | B7: ITM-075 | C7: Aluminium Motor | D7: - | E7: Pcs | F7: 3500 | G7: 3500 | H7: -7 | I7: 0 | J7: Active
A8: 4 | B8: ITM-015 | C8: Avdesh clothes | D8: - | E8: Mtr | F8: 17.5 | G8: 0 | H8: -83980.25 | I8: 0 | J8: Active
A9: 5 | B9: ITM-002 | C9: Bright clothes | D9: - | E9: F | F9: 24 | G9: 0 | H9: -14924.25 | I9: 0 | J9: Active
A10: 6 | B10: ITM-029 | C10: Chadra table | D10: - | E10: Pcs | F10: 1700 | G10: 0 | H10: -243 | I10: 0 | J10: Active
A11: 7 | B11: ITM-003 | C11: Chair cover | D11: - | E11: Pcs | F11: 55 | G11: 0 | H11: -250 | I11: 0 | J11: Active
A12: 8 | B12: ITM-089 | C12: Chinese jhalar | D12: - | E12: Pcs | F12: 42 | G12: 0 | H12: -725 | I12: 0 | J12: Active
A13: 9 | B13: ITM-055 | C13: Clothes mtr | D13: - | E13: Mtr | F13: 236 | G13: 0 | H13: -16591.5 | I13: 0 | J13: Active
A14: 10 | B14: ITM-099 | C14: Clothes mtr (pila) | D14: - | E14: Mtr | F14: 17.25 | G14: 0 | H14: -4074 | I14: 0 | J14: Active
A15: 11 | B15: ITM-104 | C15: Coffee machine | D15: - | E15: Pcs | F15: 11400 | G15: 0 | H15: -1 | I15: 0 | J15: Active
A16: 12 | B16: ITM-074 | C16: Copper Motor | D16: - | E16: Pcs | F16: 4500 | G16: 4500 | H16: -10 | I16: 0 | J16: Active
... A28: 24 | B28: ITM-083 | C28: Hitlon cover | D28: - | E28: Pcs | F28: 120 | G28: 0 | H28: -115 | I28: 0 | J28: Active
A29: 25 | B29: ITM-105 | C29: Hitlon cover saath | D29: - | F29: 18 | G29: 0 | H29: -390 | I29: 0 | J29: Active
A30: 26 | B30: ITM-006 | C30: Jhalar | D30: - | E30: Pcs | F30: 400 | G30: 0 | H30: -530 | I30: 0 | J30: Active
A31: 27 | B31: ITM-076 | C31: Jhalar 1ft | D31: - | E31: Pcs | F31: 8 | G31: 0 | H31: -396 | I31: 0 | J31: Active
A32: 28 | B32: ITM-095 | C32: Jhumar Crystal (B) | D32: - | E32: Pcs | F32: 2000 | G32: 0 | H32: -2 | I32: 0 | J32: Active
A33: 29 | B33: ITM-046 | C33: Jhumar charkor | D33: - | E33: Pcs | F33: 325 | G33: 0 | H33: -17 | I33: 0 | J33: Active
A34: 30 | B34: ITM-094 | C34: Jhumar crystal (M) | D34: - | E34: Pcs | F34: 1550 | G34: 0 | H34: -2 | I34: 0 | J34: Active
A35: 31 | B35: ITM-045 | C35: Jhumar ghanti | D35: - | E35: Pcs | F35: 180 | G35: 0 | H35: -10 | I35: 0 | J35: Active
A36: 32 | B36: ITM-069 | C36: Jhumar plastic | D36: - | E36: Pcs | F36: 200 | G36: 0 | H36: -35 | I36: 0 | J36: Active
A37: 33 | B37: ITM-071 | C37: Kalin | D37: - | E37: Pcs | F37: 1200 | G37: 0 | H37: -8 | I37: 0 | J37: Active
A38: 34 | B38: ITM-079 | C38: Kambal | D38: - | E38: Pcs | F38: 440 | G38: 0 | H38: -508 | I38: 0 | J38: Active
A39: 35 | B39: ITM-016 | C39: Khatu shree clothes | D39: - | E39: Mtr | F39: 16.5 | G39: 0 | H39: 0 | I39: 0 | J39: Active
A40: 36 | B40: ITM-059 | C40: Lais | D40: - | E40: Pcs | F40: 55 | G40: 0 | H40: -6 | I40: 0 | J40: Active
A41: 37 | B41: ITM-082 | C41: Lala lali | D41: - | E41: Pcs | F41: 1600 | G41: 0 | H41: -4 | I41: 0 | J41: Active
... A47: 43 | B47: ITM-037 | C47: Maharaja | D47: - | E47: Pcs | F47: 8500 | G47: 0 | H47: -18 | I47: 0 | J47: Active
A48: 44 | B48: ITM-049 | C48: Nagin jhumar | D48: - | F48: 275 | G48: 0 | H48: -10 | I48: 0 | J48: Active
A49: 45 | B49: ITM-005 | C49: Net clothes | D49: - | E49: F | F49: 12 | G49: 0 | H49: -10361.25 | I49: 0 | J49: Active
A50: 46 | B50: ITM-077 | C50: Net jhalar | D50: - | E50: Pcs | F50: 150 | G50: 0 | H50: -20 | I50: 0 | J50: Active
A51: 47 | B51: ITM-050 | C51: Niwar | D51: - | E51: Pcs | F51: 0 | G51: 0 | H51: -11 | I51: 0 | J51: Active
A52: 48 | B52: ITM-051 | C52: On selling | D52: - | E52: Pcs | F52: 850 | G52: 0 | H52: -14 | I52: 0 | J52: Active
A53: 49 | B53: ITM-052 | C53: On selling 10*15 | D53: - | F53: 900 | G53: 0 | H53: -24 | I53: 0 | J53: Active
A54: 50 | B54: ITM-053 | C54: On selling 15*15 | D54: - | E54: Pcs | F54: 1100 | G54: 0 | H54: -3 | I54: 0 | J54: Active
A55: 51 | B55: ITM-096 | C55: Par light | D55: - | E55: Pcs | F55: 550 | G55: 0 | H55: -80 | I55: 0 | J55: Active
A56: 52 | B56: ITM-073 | C56: Parda | D56: - | E56: Pcs | F56: 575 | G56: 0 | H56: -254 | I56: 0 | J56: Active
A57: 53 | B57: ITM-026 | C57: Parda kamdar | D57: - | E57: Pcs | F57: 800 | G57: 0 | H57: -128 | I57: 0 | J57: Active
A58: 54 | B58: ITM-027 | C58: Parda karkat | D58: - | E58: Pcs | F58: 10 | G58: 0 | H58: -1506 | I58: 0 | J58: Active
A59: 55 | B59: ITM-061 | C59: Parda sitara | D59: - | E59: Pcs | F59: 660 | G59: 0 | H59: -20 | I59: 0 | J59: Active
A60: 56 | B60: ITM-017 | C60: Patiya | D60: - | E60: Mtr | F60: 16 | G60: 0 | H60: -6132 | I60: 0 | J60: Active
A61: 57 | B61: ITM-031 | C61: Patiya kapra wala | D61: - | E61: Pcs | F61: 12 | G61: 0 | H61: -1054 | I61: 0 | J61: Active
A62: 58 | B62: ITM-013 | C62: Phle ka baki paisa | D62: - | F62: 1000 | G62: 0 | H62: -5 | I62: 0 | J62: Active
A63: 59 | B63: ITM-040 | C63: Phool seling | D63: - | E63: Pcs | F63: 1500 | G63: 0 | H63: -13 | I63: 0 | J63: Active
A64: 60 | B64: ITM-001 | C64: Plain clothes | D64: - | E64: Mtr | F64: 18 | G64: 0 | H64: -2062.75 | I64: 0 | J64: Active
A65: 61 | B65: ITM-012 | C65: Plastic chair | D65: - | E65: Pcs | F65: 295 | G65: 0 | H65: -6673 | I65: 0 | J65: Active
A66: 62 | B66: ITM-102 | C66: Poly max chair | D66: - | E66: Pcs | F66: 248 | G66: 0 | H66: -600 | I66: 0 | J66: Active
A67: 63 | B67: ITM-028 | C67: Print carpet | D67: - | E67: Pcs | F67: 5500 | G67: 0 | H67: -145 | I67: 0 | J67: Active
A68: 64 | B68: ITM-030 | C68: Print cloth | D68: - | E68: Mtr | F68: 25 | G68: 0 | H68: -3386.25 | I68: 0 | J68: Active
A69: 65 | B69: ITM-087 | C69: Raj coller | D69: - | F69: 0 | G69: 0 | H69: 0 | I69: 0 | J69: Active
A70: 66 | B70: ITM-088 | C70: Raj coller (Black) | D70: - | F70: 18000 | G70: 0 | H70: -15 | I70: 0 | J70: Active
A71: 67 | B71: ITM-008 | C71: Raj coller 150 APG | D71: - | E71: Pcs | F71: 16400 | G71: 0 | H71: -4 | I71: 0 | J71: Active
A72: 68 | B72: ITM-009 | C72: Raj coller 150ltr CPG | D72: - | E72: Pcs | F72: 18500 | G72: 0 | H72: -6 | I72: 0 | J72: Active
A73: 69 | B73: ITM-065 | C73: Raj cooler white copper | D73: - | E73: Pcs | F73: 23000 | G73: 0 | H73: -3 | I73: 0 | J73: Active
A74: 70 | B74: ITM-014 | C74: Raj cooler 150ltr white copper | D74: - | E74: Pcs | F74: 24000 | G74: 0 | H74: -20 | I74: 0 | J74: Active
A75: 71 | B75: ITM-022 | C75: Raj cooler 150ltr white copper 3 blade | D75: - | E75: Pcs | F75: 6 | G75: 0 | H75: -4 | I75: 0 | J75: Active
A76: 72 | B76: ITM-039 | C76: Raj cooler 150ltr white copper 4 blade | D76: - | E76: Pcs | F76: 23500 | G76: 0 | H76: -3 | I76: 0 | J76: Active
A77: 73 | B77: ITM-043 | C77: Rani yellow phool seling | D77: - | E77: Pcs | F77: 2000 | G77: 0 | H77: -28 | I77: 0 | J77: Active
A78: 74 | B78: ITM-042 | C78: Rani yellow selling | D78: - | E78: Pcs | F78: 2400 | G78: 0 | H78: -23 | I78: 0 | J78: Active
A79: 75 | B79: ITM-062 | C79: Ribbon | D79: - | E79: Pcs | F79: 130 | G79: 0 | H79: -11 | I79: 0 | J79: Active
A80: 76 | B80: ITM-038 | C80: Round cover | D80: - | E80: Pcs | F80: 225 | G80: 0 | H80: -300 | I80: 0 | J80: Active
A81: 77 | B81: ITM-080 | C81: Round cover jhalar | D81: - | E81: Pcs | F81: 290 | G81: 0 | H81: -12 | I81: 0 | J81: Active
A82: 78 | B82: ITM-041 | C82: Round gulaab selling | D82: - | E82: Pcs | F82: 2400 | G82: 0 | H82: -12 | I82: 0 | J82: Active
... A88: 84 | B88: ITM-018 | C88: Sidhi | D88: - | E88: Pcs | F88: 1700 | G88: 0 | H88: -22 | I88: 0 | J88: Active
A89: 85 | B89: ITM-021 | C89: Sidhi 10ft | D89: - | F89: 1600 | G89: 0 | H89: -55 | I89: 0 | J89: Active
A90: 86 | B90: ITM-020 | C90: Sidhi 12ft | D90: - | E90: Pcs | F90: 0 | G90: 0 | H90: 0 | I90: 0 | J90: Active
A91: 87 | B91: ITM-019 | C91: Sidhi chota | D91: - | E91: Pcs | F91: 1125 | G91: 0 | H91: -65 | I91: 0 | J91: Active
A92: 88 | B92: ITM-103 | C92: Strip light | D92: - | E92: Pcs | F92: 850 | G92: 0 | H92: -1 | I92: 0 | J92: Active
A93: 89 | B93: ITM-010 | C93: Sundaram carpet | D93: - | E93: Pcs | F93: 6200 | G93: 0 | H93: -23 | I93: 0 | J93: Active
A94: 90 | B94: ITM-036 | C94: Sundaram carpet green | D94: - | F94: 5700 | G94: 0 | H94: -3 | I94: 0 | J94: Active
A95: 91 | B95: ITM-035 | C95: Sundaram carpet red | D95: - | F95: 6000 | G95: 0 | H95: -2 | I95: 0 | J95: Active
A96: 92 | B96: ITM-025 | C96: Table square | D96: - | E96: Pcs | F96: 2500 | G96: 0 | H96: -65 | I96: 0 | J96: Active
A97: 93 | B97: ITM-068 | C97: Total Samman | D97: - | F97: 57000 | G97: 0 | H97: -1 | I97: 0 | J97: Active
A98: 94 | B98: ITM-032 | C98: Tripal 18*24 | D98: - | E98: Pcs | F98: 1500 | G98: 0 | H98: -55 | I98: 0 | J98: Active
A99: 95 | B99: ITM-058 | C99: Tripal 18*24 (170 gsm) | D99: - | E99: Pcs | F99: 1500 | G99: 0 | H99: -29 | I99: 0 | J99: Active
A100: 96 | B100: ITM-033 | C100: Tripal 21*30 | D100: - | F100: 2250 | G100: 0 | H100: -21 | I100: 0 | J100: Active
A101: 97 | B101: ITM-056 | C101: Tripal 21*30 (170gsm) | D101: - | E101: Pcs | F101: 1850 | G101: 0 | H101: -2204 | I101: 0 | J101: Active
A102: 98 | B102: ITM-072 | C102: Tripal 24*30 | D102: - | E102: Pcs | F102: 9 | G102: 0 | H102: -5296 | I102: 0 | J102: Active
A103: 99 | B103: ITM-057 | C103: Tripal 24*30 (170 gsm) | D103: - | E103: Pcs | F103: 2300 | G103: 0 | H103: -3 | I103: 0 | J103: Active
A104: 100 | B104: ITM-100 | C104: Tripal 24*36 | D104: - | E104: Pcs | F104: 0 | G104: 0 | H104: -2 | I104: 0 | J104: Active
A105: 101 | B105: ITM-063 | C105: Triple 24*36 | D105: - | E105: Pcs | F105: 2650 | G105: 0 | H105: -8 | I105: 0 | J105: Active
A106: 102 | B106: ITM-067 | C106: Triple 30*36 | D106: - | F106: 3450 | G106: 0 | H106: -2 | I106: 0 | J106: Active
A107: 103 | B107: ITM-070 | C107: Umbrella chota | D107: - | E107: Pcs | F107: 460 | G107: 0 | H107: -34 | I107: 0 | J107: Active
A108: 104 | B108: ITM-011 | C108: V.I.P chair | D108: - | E108: Pcs | F108: 12000 | G108: 0 | H108: -346 | I108: 0 | J108: Active
A109: 105 | B109: ITM-107 | C109: White safeda | D109: - | E109: Mtr | F109: 24.4 | G109: 0 | H109: -65 | I109: 0 | J109: Active
A110: 106 | B110: ITM-024 | C110: clothes | D110: - | E110: Mtr | F110: 16.75 | G110: 0 | H110: -310973.75 | I110: 0 | J110: Active
A111: 107 | B111: ITM-066 | C111: clothes 5.7kg | D111: - | E111: Mtr | F111: 15.5 | G111: 0 | H111: -12430.25 | I111: 0 | J111: Active
G112: Total | H112: =SUM(H5:H111) -> -523824.35 | I112: =SUM(I5:I111) -> 0

Sheet All Transactions Register
A1: Kushwaha Tent Ajency — Complete Transactions Register
A2: Chronological audit of all 391 business transactions (Sales, Receipts, Payments, Returns)
A4: Sl No | B4: Txn ID | C4: Date | D4: Voucher Type | E4: Ref / Inv No | F4: Party Name | G4: Inflow / Credit (₹) | H4: Outflow / Debit (₹) | I4: Balance Amount (₹) | J4: Payment Mode | K4: Description / Remarks
A5: 1 | B5: 1 | C5: 2023-02-11 | D5: Sale | E5: 1 | F5: Rajiv tent house | G5: 30000 | H5: 0 | I5: 102400 | J5: Cash
A6: 2 | B6: 2 | C6: 2023-02-11 | D6: Payment In (Receipt) | E6: 1 | F6: Rajiv tent house | G6: 20000 | H6: 0 | I6: 0 | J6: Cash
A7: 3 | B7: 3 | C7: 2023-02-12 | D7: Sale | E7: 2 | F7: Raja tent house | G7: 50000 | H7: 0 | I7: 63490 | J7: Cash
A8: 4 | B8: 4 | C8: 2023-02-12 | D8: Sale | E8: 3 | F8: Pardeep kumar | G8: 0 | H8: 0 | I8: 15709.5 | J8: Cash
A9: 5 | B9: 5 | C9: 2023-02-12 | D9: Sale | E9: 4 | F9: R.D.S palace | G9: 0 | H9: 0 | I9: 50000 | J9: Cash
A10: 6 | B10: 6 | C10: 2023-02-14 | D10: Sale | E10: 5 | F10: gulshan tent house | G10: 2000 | H10: 0 | I10: 34000 | J10: Cash
A11: 7 | B11: 8 | C11: 2023-02-21 | D11: Sale | E11: 7 | F11: Pankaj tent house | G11: 0 | H11: 0 | I11: 28647.5 | J11: Cash
A12: 8 | B12: 9 | C12: 2023-03-07 | D12: Sale | E12: 8 | F12: Sonu kumar | G12: 73000 | H12: 0 | I12: 50000 | J12: Cash | K12: 5000- Account deposit 45000- cash
A13: 9 | B13: 10 | C13: 2023-04-05 | D13: Sale | E13: 9 | F13: Anil tent house | G13: 24000 | H13: 0 | I13: 21600 | J13: Cash
A14: 10 | B14: 11 | C14: 2023-04-09 | D14: Sale | E14: 10 | F14: shir ram tent house | G14: 65500 | H14: 0 | I14: 0 | J14: Cash
A15: 11 | B15: 12 | C15: 2023-04-11 | D15: Sale | E15: 11 | F15: Pankaj tent house | G15: 58314 | H15: 0 | I15: 133263.94 | J15: Cash
A16: 12 | B16: 13 | C16: 2023-04-14 | D16: Sale | E16: 12 | F16: Rajiv tent house | G16: 34000 | H16: 0 | I16: 54000 | J16: Cash
A17: 13 | B17: 14 | C17: 2023-04-14 | D17: Sale | E17: 13 | F17: Birju singh | G17: 50000 | H17: 0 | I17: 50000 | J17: Cash
A18: 14 | B18: 15 | C18: 2023-04-14 | D18: Sale | E18: 14 | F18: jitendra tent house | G18: 90000 | H18: 0 | I18: 10000 | J18: Cash
A19: 15 | B19: 17 | C19: 2023-04-16 | D19: Payment In (Receipt) | E19: 2 | F19: Guddu shaa | G19: 25000 | H19: 0 | I19: 0 | J19: Cash
A20: 16 | B20: 18 | C20: 2023-04-19 | D20: Sale | E20: 16 | F20: Cafe D3 | G20: 37000 | H20: 0 | I20: 0 | J20: Cash
A21: 17 | B21: 19 | C21: 2023-04-21 | D21: Sale | E21: 17 | F21: Chauhan tent house | G21: 84000 | H21: 0 | I21: 0 | J21: Cash
A22: 18 | B22: 20 | C22: 2023-04-24 | D22: Sale | E22: 18 | F22: Pankaj tent house | G22: 0 | H22: 0 | I22: 40945.63 | J22: Cash
A23: 19 | B23: 21 | C23: 2023-04-28 | D23: Sale | E23: 19 | F23: Pankaj tent house | G23: 0 | H23: 0 | I23: 23790.75 | J23: Cash
A24: 20 | B24: 22 | C24: 2023-05-09 | D24: Sale | E24: 20 | F24: Pankaj tent house | G24: 0 | H24: 0 | I24: 104877.5 | J24: Cash
... A55: 51 | B55: 53 | C55: 2024-02-20 | D55: Sale | E55: 45 | F55: New kushwaha Tent Ajency Mahnar | G55: 0 | H55: 0 | I55: 134075.28 | J55: Cash
A56: 52 | B56: 54 | C56: 2024-02-20 | D56: Payment In (Receipt) | E56: 6 | F56: New kushwaha Tent Ajency Mahnar | G56: 26000 | H56: 0 | I56: 0 | J56: Cash | K56: 600 rajkumar thela 400 thela cash -25000 received hua
A57: 53 | B57: 55 | C57: 2024-02-22 | D57: Payment In (Receipt) | E57: 7 | F57: New kushwaha Tent Ajency Mahnar | G57: 80000 | H57: 0 | I57: 0 | J57: Cash
A58: 54 | B58: 58 | C58: 2024-02-23 | D58: Payment In (Receipt) | E58: 8 | F58: New kushwaha Tent Ajency Mahnar | G58: 10000 | H58: 0 | I58: 0 | J58: Cheque
A59: 55 | B59: 56 | C59: 2024-02-25 | D59: Sale | E59: 46 | F59: D green | G59: 0 | H59: 0 | I59: 47000 | J59: Cash
A60: 56 | B60: 57 | C60: 2024-02-25 | D60: Sale | E60: 47 | F60: New kushwaha Tent Ajency Mahnar | G60: 0 | H60: 0 | I60: 176167.4 | J60: Cash
A61: 57 | B61: 59 | C61: 2024-02-26 | D61: Sale | E61: 48 | F61: Maharani electric and tent spare | G61: 0 | H61: 0 | I61: 73206.5 | J61: Cash
A62: 58 | B62: 60 | C62: 2024-02-28 | D62: Payment In (Receipt) | E62: 9 | F62: New kushwaha Tent Ajency Mahnar | G62: 65000 | H62: 0 | I62: 0 | J62: Cash
A63: 59 | B63: 61 | C63: 2024-02-28 | D63: Sale | E63: 49 | F63: New kushwaha Tent Ajency Mahnar | G63: 0 | H63: 0 | I63: 7150 | J63: Cash
A64: 60 | B64: 78 | C64: 2024-02-28 | D64: Payment In (Receipt) | E64: 18 | F64: D green | G64: 25000 | H64: 0 | I64: 0 | J64: Kotak Mahindra Bank
A65: 61 | B65: 62 | C65: 2024-03-01 | D65: Payment In (Receipt) | E65: 10 | F65: New kushwaha Tent Ajency Mahnar | G65: 15500 | H65: 0 | I65: 0 | J65: Cash
A66: 62 | B66: 63 | C66: 2024-03-02 | D66: Sale | E66: 50 | F66: New kushwaha Tent Ajency Mahnar | G66: 0 | H66: 0 | I66: 106490 | J66: Cash
A67: 63 | B67: 64 | C67: 2024-03-04 | D67: Payment In (Receipt) | E67: 11 | F67: New kushwaha Tent Ajency Mahnar | G67: 40000 | H67: 0 | I67: 0 | J67: Cash
A68: 64 | B68: 65 | C68: 2024-03-05 | D68: Sale | E68: 51 | F68: New kushwaha Tent Ajency Mahnar | G68: 0 | H68: 0 | I68: 288653 | J68: Cash
... A91: 87 | B91: 89 | C91: 2024-04-05 | D91: Sale | E91: 63 | F91: New kushwaha Tent Ajency Mahnar | G91: 0 | H91: 0 | I91: 57818.13 | J91: Cash
A92: 88 | B92: 90 | C92: 2024-04-06 | D92: Payment In (Receipt) | E92: 23 | F92: New kushwaha Tent Ajency Mahnar | G92: 86000 | H92: 0 | I92: 0 | J92: Cash | K92: chair 100p
A93: 89 | B93: 91 | C93: 2024-04-07 | D93: Payment In (Receipt) | E93: 24 | F93: New kushwaha Tent Ajency Mahnar | G93: 62000 | H93: 0 | I93: 0 | J93: Cash
A94: 90 | B94: 92 | C94: 2024-04-07 | D94: Payment In (Receipt) | E94: 25 | F94: New kushwaha Tent Ajency Mahnar | G94: 57000 | H94: 0 | I94: 0 | J94: Cash
A95: 91 | B95: 93 | C95: 2024-04-07 | D95: Sale | E95: 64 | F95: New kushwaha Tent Ajency Mahnar | G95: 0 | H95: 0 | I95: 88150 | J95: Cash
A96: 92 | B96: 94 | C96: 2024-04-10 | D96: Sale | E96: 65 | F96: New kushwaha Tent Ajency Mahnar | G96: 0 | H96: 0 | I96: 249845.63 | J96: Cash
A97: 93 | B97: 95 | C97: 2024-04-10 | D97: Sale | E97: 66 | F97: Maharani electric and tent spare | G97: 0 | H97: 0 | I97: 145028.69 | J97: Cash
A98: 94 | B98: 96 | C98: 2024-04-11 | D98: Payment In (Receipt) | E98: 26 | F98: Sohan Dj Sound | G98: 10000 | H98: 0 | I98: 0 | J98: Cash
A99: 95 | B99: 97 | C99: 2024-04-12 | D99: Sale | E99: 67 | F99: Sohan Dj Sound | G99: 0 | H99: 0 | I99: 71191 | J99: Cash
A100: 96 | B100: 98 | C100: 2024-04-12 | D100: Sale | E100: 68 | F100: New kushwaha Tent Ajency Mahnar | G100: 0 | H100: 0 | I100: 132669.5 | J100: Cash
A101: 97 | B101: 99 | C101: 2024-04-12 | D101: Payment In (Receipt) | E101: 27 | F101: New kushwaha Tent Ajency Mahnar | G101: 50000 | H101: 0 | I101: 0 | J101: Kotak Mahindra Bank
A102: 98 | B102: 100 | C102: 2024-04-12 | D102: Sale | E102: 69 | F102: New kushwaha Tent Ajency Mahnar | G102: 0 | H102: 0 | I102: 43057 | J102: Cash
A103: 99 | B103: 102 | C103: 2024-04-12 | D103: Payment In (Receipt) | E103: 28 | F103: New kushwaha Tent Ajency Mahnar | G103: 135000 | H103: 0 | I103: 0 | J103: Cash
A104: 100 | B104: 101 | C104: 2024-04-13 | D104: Sale | E104: 70 | F104: Sohan Dj Sound | G104: 0 | H104: 0 | I104: 11976.25 | J104: Cash
A105: 101 | B105: 103 | C105: 2024-04-14 | D105: Sale Return (Credit Note) | E105: 1 | F105: New kushwaha Tent Ajency Mahnar | G105: 0 | H105: 0 | I105: 76500 | J105: Cash | K105: 200 hajipur 100 jandha
A106: 102 | B106: 133 | C106: 2024-04-14 | D106: Sale | E106: 79 | F106: R.D.S palace | G106: 0 | H106: 0 | I106: 26512 | J106: Cash
A107: 103 | B107: 104 | C107: 2024-04-15 | D107: Payment In (Receipt) | E107: 29 | F107: Sohan Dj Sound | G107: 20000 | H107: 0 | I107: 0 | J107: Cash
A108: 104 | B108: 105 | C108: 2024-04-17 | D108: Sale | E108: 71 | F108: New shrivastav Tent Ajency | G108: 5000 | H108: 0 | I108: 3010 | J108: Cash
A109: 105 | B109: 106 | C109: 2024-04-17 | D109: Payment In (Receipt) | E109: 30 | F109: New kushwaha Tent Ajency Mahnar | G109: 150000 | H109: 0 | I109: 0 | J109: Cash
A110: 106 | B110: 110 | C110: 2024-04-17 | D110: Sale | E110: 73 | F110: New kushwaha Tent Ajency Mahnar | G110: 0 | H110: 0 | I110: 88625.13 | J110: Cash
A111: 107 | B111: 107 | C111: 2024-04-18 | D111: Payment In (Receipt) | E111: 31 | F111: New kushwaha Tent Ajency Mahnar | G111: 20000 | H111: 0 | I111: 0 | J111: Kotak Mahindra Bank
A112: 108 | B112: 108 | C112: 2024-04-18 | D112: Payment In (Receipt) | E112: 32 | F112: New kushwaha Tent Ajency Mahnar | G112: 3000 | H112: 0 | I112: 0 | J112: Cash
A113: 109 | B113: 109 | C113: 2024-04-18 | D113: Sale | E113: 72 | F113: Maharani electric and tent spare | G113: 0 | H113: 0 | I113: 183358.19 | J113: Cash
A114: 110 | B114: 111 | C114: 2024-04-19 | D114: Sale | E114: 74 | F114: New shrivastav Tent Ajency | G114: 5000 | H114: 0 | I114: 2800 | J114: Cash
A115: 111 | B115: 112 | C115: 2024-04-20 | D115: Payment In (Receipt) | E115: 33 | F115: Sohan Dj Sound | G115: 30000 | H115: 0 | I115: 0 | J115: Cash
A116: 112 | B116: 113 | C116: 2024-04-20 | D116: Sale | E116: 75 | F116: New shrivastav Tent Ajency | G116: 0 | H116: 0 | I116: 2250 | J116: Cash
A117: 113 | B117: 114 | C117: 2024-04-20 | D117: Payment In (Receipt) | E117: 34 | F117: New shrivastav Tent Ajency | G117: 5000 | H117: 0 | I117: 0 | J117: Cash
... A133: 129 | B133: 130 | C133: 2024-05-02 | D133: Payment In (Receipt) | E133: 47 | F133: New kushwaha Tent Ajency Mahnar | G133: 40000 | H133: 0 | I133: 0 | J133: Kotak Mahindra Bank
A134: 130 | B134: 131 | C134: 2024-05-02 | D134: Payment In (Receipt) | E134: 48 | F134: New kushwaha Tent Ajency Mahnar | G134: 10000 | H134: 0 | I134: 0 | J134: Cash | K134: gadi bhada or tampu bada or parda solve total bada
A135: 131 | B135: 132 | C135: 2024-05-03 | D135: Payment In (Receipt) | E135: 49 | F135: Sohan Dj Sound | G135: 20000 | H135: 0 | I135: 0 | J135: Cash
A136: 132 | B136: 137 | C136: 2024-05-07 | D136: Payment In (Receipt) | E136: 51 | F136: New kushwaha Tent Ajency Mahnar | G136: 35000 | H136: 0 | I136: 0 | J136: Cash
A137: 133 | B137: 134 | C137: 2024-05-09 | D137: Payment In (Receipt) | E137: 50 | F137: Sohan Dj Sound | G137: 10000 | H137: 0 | I137: 0 | J137: Cash
A138: 134 | B138: 135 | C138: 2024-05-12 | D138: Sale | E138: 80 | F138: Cafe D3 | G138: 0 | H138: 0 | I138: 22500 | J138: Cash
A139: 135 | B139: 136 | C139: 2024-05-12 | D139: Sale | E139: 81 | F139: New kushwaha Tent Ajency Mahnar | G139: 33700 | H139: 0 | I139: 91706.5 | J139: Cash | K139: table square - 10 p aaya hajipur green carpet- 1 p
A140: 136 | B140: 138 | C140: 2024-05-13 | D140: Payment In (Receipt) | E140: 52 | F140: New kushwaha Tent Ajency Mahnar | G140: 26000 | H140: 0 | I140: 0 | J140: Cash | K140: Add Mahnar se hajipur tampu bhada -500
A141: 137 | B141: 139 | C141: 2024-05-13 | D141: Payment In (Receipt) | E141: 53 | F141: Sohan Dj Sound | G141: 10000 | H141: 0 | I141: 0 | J141: Cash
A142: 138 | B142: 141 | C142: 2024-05-13 | D142: Payment In (Receipt) | E142: 55 | F142: New kushwaha Tent Ajency Mahnar | G142: 111300 | H142: 0 | I142: 0 | J142: Cash
A143: 139 | B143: 147 | C143: 2024-05-16 | D143: Sale | E143: 84 | F143: Sohan Dj Sound | G143: 0 | H143: 0 | I143: 57000 | J143: Cash
A144: 140 | B144: 140 | C144: 2024-05-21 | D144: Payment In (Receipt) | E144: 54 | F144: New kushwaha Tent Ajency Mahnar | G144: 20000 | H144: 0 | I144: 0 | J144: Cash
A145: 141 | B145: 185 | C145: 2024-05-22 | D145: Sale | E145: 101 | F145: Abhishek and Arushi Enterprises | G145: 40320 | H145: 0 | I145: 0 | J145: Kotak Mahindra Bank
A146: 142 | B146: 142 | C146: 2024-05-28 | D146: Payment In (Receipt) | E146: 56 | F146: New kushwaha Tent Ajency Mahnar | G146: 10000 | H146: 0 | I146: 0 | J146: Kotak Mahindra Bank
A147: 143 | B147: 143 | C147: 2024-05-28 | D147: Payment In (Receipt) | E147: 57 | F147: New kushwaha Tent Ajency Mahnar | G147: 20000 | H147: 0 | I147: 0 | J147: Cash
A148: 144 | B148: 145 | C148: 2024-05-28 | D148: Sale | E148: 82 | F148: New kushwaha Tent Ajency Mahnar | G148: 0 | H148: 0 | I148: 125000 | J148: Cash
A149: 145 | B149: 146 | C149: 2024-06-05 | D149: Sale | E149: 83 | F149: Maharani electric and tent spare | G149: 0 | H149: 0 | I149: 57349 | J149: Cash
A150: 146 | B150: 148 | C150: 2024-06-05 | D150: Sale | E150: 85 | F150: Sohan Dj Sound | G150: 0 | H150: 0 | I150: 29768 | J150: Cash
A151: 147 | B151: 149 | C151: 2024-06-05 | D151: Payment In (Receipt) | E151: 59 | F151: Sohan Dj Sound | G151: 10000 | H151: 0 | I151: 0 | J151: Kotak Mahindra Bank
A152: 148 | B152: 144 | C152: 2024-06-06 | D152: Payment In (Receipt) | E152: 58 | F152: New kushwaha Tent Ajency Mahnar | G152: 20000 | H152: 0 | I152: 0 | J152: Cash | K152: cash+A/c
A153: 149 | B153: 150 | C153: 2024-06-07 | D153: Payment In (Receipt) | E153: 60 | F153: Sohan Dj Sound | G153: 5000 | H153: 0 | I153: 0 | J153: Cash
A154: 150 | B154: 151 | C154: 2024-06-07 | D154: Sale | E154: 86 | F154: New kushwaha Tent Ajency Mahnar | G154: 0 | H154: 0 | I154: 107453 | J154: Cash
A155: 151 | B155: 184 | C155: 2024-06-18 | D155: Sale | E155: 100 | F155: Abhishek and Arushi Enterprises | G155: 40320 | H155: 0 | I155: 0 | J155: Kotak Mahindra Bank
A156: 152 | B156: 152 | C156: 2024-06-19 | D156: Payment In (Receipt) | E156: 61 | F156: New kushwaha Tent Ajency Mahnar | G156: 49000 | H156: 0 | I156: 0 | J156: Cash
A157: 153 | B157: 153 | C157: 2024-06-21 | D157: Payment In (Receipt) | E157: 62 | F157: Sohan Dj Sound | G157: 8000 | H157: 0 | I157: 0 | J157: Cash
A158: 154 | B158: 154 | C158: 2024-06-22 | D158: Payment In (Receipt) | E158: 63 | F158: New kushwaha Tent Ajency Mahnar | G158: 2000 | H158: 0 | I158: 0 | J158: Cash | K158: auto+ gadi bhada chair ka
A159: 155 | B159: 155 | C159: 2024-06-22 | D159: Sale | E159: 87 | F159: New kushwaha Tent Ajency Mahnar | G159: 0 | H159: 0 | I159: 3900 | J159: Cash
A160: 156 | B160: 156 | C160: 2024-06-23 | D160: Sale | E160: 88 | F160: Maharani electric and tent spare | G160: 0 | H160: 0 | I160: 85165.13 | J160: Cash
A161: 157 | B161: 157 | C161: 2024-06-23 | D161: Sale | E161: 89 | F161: Sohan Dj Sound | G161: 0 | H161: 0 | I161: 5776 | J161: Cash
A162: 158 | B162: 158 | C162: 2024-06-24 | D162: Sale | E162: 90 | F162: New kushwaha Tent Ajency Mahnar | G162: 0 | H162: 0 | I162: 54551 | J162: Cash
A163: 159 | B163: 159 | C163: 2024-07-02 | D163: Payment In (Receipt) | E163: 64 | F163: New kushwaha Tent Ajency Mahnar | G163: 44000 | H163: 0 | I163: 0 | J163: Cash
A164: 160 | B164: 160 | C164: 2024-07-03 | D164: Payment In (Receipt) | E164: 65 | F164: Sohan Dj Sound | G164: 10000 | H164: 0 | I164: 0 | J164: Cash
A165: 161 | B165: 161 | C165: 2024-07-05 | D165: Sale | E165: 91 | F165: Hariyali Machinery and Electric | G165: 30000 | H165: 0 | I165: 26196 | J165: Kotak Mahindra Bank
A166: 162 | B166: 162 | C166: 2024-07-05 | D166: Sale | E166: 92 | F166: New kushwaha Tent Ajency Mahnar | G166: 0 | H166: 0 | I166: 86076 | J166: Cash
A167: 163 | B167: 163 | C167: 2024-07-05 | D167: Payment In (Receipt) | E167: 66 | F167: New kushwaha Tent Ajency Mahnar | G167: 38000 | H167: 0 | I167: 0 | J167: Cash
A168: 164 | B168: 164 | C168: 2024-07-06 | D168: Payment In (Receipt) | E168: 67 | F168: New kushwaha Tent Ajency Mahnar | G168: 40000 | H168: 0 | I168: 0 | J168: Cash | K168: payment chair wala
...
